{
  "date": "2026-04-10",
  "lastUpdated": "2026-04-10T19:45:24.674Z",
  "operations": [
    {
      "id": "tg-almayadeen-364659",
      "time": "2026-04-10T19:41:33+00:00",
      "title": "لبنان: المقاومة الإسلامية: استهدفنا تجمّعاً لآليات وجنود \"جيش\" العدو الإسرائيلي عند مثلث التحرير بصليةٍ صاروخية",
      "description": "لبنان: المقاومة الإسلامية: استهدفنا تجمّعاً لآليات وجنود \"جيش\" العدو الإسرائيلي عند مثلث التحرير بصليةٍ صاروخية",
      "category": "hezbollah",
      "status": "confirmed",
      "source": "@almayadeen",
      "needsReview": false
    },
    {
      "id": "tg-almayadeen-364658",
      "time": "2026-04-10T19:36:21+00:00",
      "title": "لبنان: المقاومة الإسلامية: استهدفنا تجمّعات لآليات وجنود \"جيش\" العدو الإسرائيلي في محيط مدرسة الإشراق في مدينة بنت جبيل بصلياتٍ صاروخيّة وقذائف المدفعية على دفعات",
      "description": "لبنان: المقاومة الإسلامية: استهدفنا تجمّعات لآليات وجنود \"جيش\" العدو الإسرائيلي في محيط مدرسة الإشراق في مدينة بنت جبيل بصلياتٍ صاروخيّة وقذائف المدفعية على دفعات",
      "category": "hezbollah",
      "status": "confirmed",
      "source": "@almayadeen",
      "needsReview": false,
      "lat": 33.29,
      "lon": 35.42
    },
    {
      "id": "tg-mmirleb-14838",
      "time": "2026-04-10T19:35:07+00:00",
      "title": "دفاعًا عن لبنان وشعبه، وردًّا على خرق العدوّ لاتفاق وقف إطلاق النار، واعتداءاته المتكرّرة على قرى ال",
      "description": "&rlm;  &rlm;&rlm;  دفاعًا عن لبنان وشعبه، وردًّا على خرق العدوّ لاتفاق وقف إطلاق النار، واعتداءاته المتكرّرة على قرى الجنوب، وبعدما التزمت المقاومة بوقف النار ولم يلتزم به العدوّ، استهدف مجاهدو المُقاومة الإسلاميّة عند السّاعة 21:00 الجمعة 10-04-2026 تجمّعًا لآليات وجنود جيش العدوّ الإسرائيليّ عند م",
      "category": "hezbollah",
      "status": "confirmed",
      "source": "@mmirleb",
      "needsReview": false
    },
    {
      "id": "tg-almayadeen-364657",
      "time": "2026-04-10T19:34:53+00:00",
      "title": "إيران: مسيرات حاشدة في المدن الإيرانية لإحياء الليلة الأخيرة من ذكرى أربعين الشهيد القائد الأمة السيد علي خامنئي",
      "description": "إيران: مسيرات حاشدة في المدن الإيرانية لإحياء الليلة الأخيرة من ذكرى أربعين الشهيد القائد الأمة السيد علي خامنئي",
      "category": "iran",
      "status": "confirmed",
      "source": "@almayadeen",
      "needsReview": false
    },
    {
      "id": "tg-almayadeen-364656",
      "time": "2026-04-10T19:33:37+00:00",
      "title": "إيران: مسيرات حاشدة في طهران في إحياء الليلة الأخيرة من ذكرى أربعين الشهيد القائد الأمة السيد علي خامنئي",
      "description": "إيران: مسيرات حاشدة في طهران في إحياء الليلة الأخيرة من ذكرى أربعين الشهيد القائد الأمة السيد علي خامنئي",
      "category": "iran",
      "status": "confirmed",
      "source": "@almayadeen",
      "needsReview": false
    },
    {
      "id": "tg-almayadeen-364655",
      "time": "2026-04-10T19:33:04+00:00",
      "title": "لبنان: رئيس حزب التيار العربي شاكر البرجاوي للميادين: ثبات الموقف الإيراني سيلزم ترامب بفرض وقف إطلاق النار في لبنان على نتنياهو",
      "description": "لبنان: رئيس حزب التيار العربي شاكر البرجاوي للميادين: ثبات الموقف الإيراني سيلزم ترامب بفرض وقف إطلاق النار في لبنان على نتنياهو",
      "category": "iran",
      "status": "confirmed",
      "source": "@almayadeen",
      "needsReview": false
    },
    {
      "id": "tg-mmirleb-14835",
      "time": "2026-04-10T19:30:00+00:00",
      "title": "دفاعًا عن لبنان وشعبه، وردًّا على خرق العدوّ لاتفاق وقف إطلاق النار، واعتداءاته المتكرّرة على الضاحي",
      "description": "&rlm;  &rlm;&rlm;  دفاعًا عن لبنان وشعبه، وردًّا على خرق العدوّ لاتفاق وقف إطلاق النار، واعتداءاته المتكرّرة على الضاحية الجنوبية لبيروت، وبعدما التزمت المقاومة بوقف النار ولم يلتزم به العدوّ، استهدف مجاهدو المُقاومة الإسلاميّة عند السّاعة 21:10 الجمعة 10-04-2026  بنى تحتيّة تتبع لجيش العدوّ الإسرائ",
      "category": "hezbollah",
      "status": "confirmed",
      "source": "@mmirleb",
      "needsReview": false,
      "lat": 33.89,
      "lon": 35.51
    },
    {
      "id": "tg-almayadeen-364654",
      "time": "2026-04-10T19:28:17+00:00",
      "title": "وسائل إعلام إسرائيلية: منذ ساعات الصباح تم تسجيل حوالى 50 إطلاقاً من لبنان باتجاه مستوطنات الشمال",
      "description": "وسائل إعلام إسرائيلية: منذ ساعات الصباح تم تسجيل حوالى 50 إطلاقاً من لبنان باتجاه مستوطنات الشمال",
      "category": "statements",
      "status": "confirmed",
      "source": "@almayadeen",
      "needsReview": false,
      "lat": 33.1,
      "lon": 35.4
    },
    {
      "id": "tg-almayadeen-364653",
      "time": "2026-04-10T19:27:48+00:00",
      "title": "لبنان: مراسل الميادين في الجنوب: صلية صاروخية تنطلق من لبنان باتجاه الأراضي المحتلة",
      "description": "لبنان: مراسل الميادين في الجنوب: صلية صاروخية تنطلق من لبنان باتجاه الأراضي المحتلة",
      "category": "statements",
      "status": "confirmed",
      "source": "@almayadeen",
      "needsReview": false
    },
    {
      "id": "tg-almayadeen-364652",
      "time": "2026-04-10T19:27:10+00:00",
      "title": "وسائل إعلام إسرائيلية: إطلاق 10 صواريخ من لبنان باتجاه \"كريات شمونة\"",
      "description": "وسائل إعلام إسرائيلية: إطلاق 10 صواريخ من لبنان باتجاه \"كريات شمونة\"",
      "category": "hezbollah",
      "status": "confirmed",
      "source": "@almayadeen",
      "needsReview": false,
      "lat": 33.21,
      "lon": 35.57
    },
    {
      "id": "tg-almayadeen-364651",
      "time": "2026-04-10T19:25:28+00:00",
      "title": "لبنان: الشيخ حمود: قلتم إنكم ستفاوضون فما هي الأوراق التي في أيديكم وكيف ستجلسون في مفاوضات أنتم فيها عراة",
      "description": "لبنان: الشيخ حمود: قلتم إنكم ستفاوضون فما هي الأوراق التي في أيديكم وكيف ستجلسون في مفاوضات أنتم فيها عراة",
      "category": "political",
      "status": "confirmed",
      "source": "@almayadeen",
      "needsReview": false
    },
    {
      "id": "tg-almayadeen-364650",
      "time": "2026-04-10T19:25:10+00:00",
      "title": "لبنان: الشيخ حمود: لقد صمدت المقاومة صموداً أسطورياً أربعين يوماً ولم يستطع العدو أن يتقدم في القرى الحدوية ألا يرون ذلك؟",
      "description": "لبنان: الشيخ حمود: لقد صمدت المقاومة صموداً أسطورياً أربعين يوماً ولم يستطع العدو أن يتقدم في القرى الحدوية ألا يرون ذلك؟",
      "category": "statements",
      "status": "confirmed",
      "source": "@almayadeen",
      "needsReview": false
    },
    {
      "id": "tg-almayadeen-364649",
      "time": "2026-04-10T19:23:12+00:00",
      "title": "لبنان: الشيخ حمود: &rlm;إن لم يتراجع سلام عن هذا الكلام ويوضح مقصده فهو في الموقع مثل نتنياهو تماماً عدوٌ للبنان بكل مكوناته",
      "description": "لبنان: الشيخ حمود: &rlm;إن لم يتراجع سلام عن هذا الكلام ويوضح مقصده فهو في الموقع مثل نتنياهو تماماً عدوٌ للبنان بكل مكوناته",
      "category": "statements",
      "status": "confirmed",
      "source": "@almayadeen",
      "needsReview": false
    },
    {
      "id": "tg-almayadeen-364648",
      "time": "2026-04-10T19:22:40+00:00",
      "title": "لبنان: الشيخ حمود: رئيسا الجمهورية والحكومة بررا للعدو اعتداءه خاصة فيما تسرب عن سلام بأنه قال إن ما استُهدف في بيروت هو مخازن سلاح",
      "description": "لبنان: الشيخ حمود: رئيسا الجمهورية والحكومة بررا للعدو اعتداءه خاصة فيما تسرب عن سلام بأنه قال إن ما استُهدف في بيروت هو مخازن سلاح",
      "category": "statements",
      "status": "confirmed",
      "source": "@almayadeen",
      "needsReview": false,
      "lat": 33.89,
      "lon": 35.51
    },
    {
      "id": "tg-almayadeen-364647",
      "time": "2026-04-10T19:21:24+00:00",
      "title": "لبنان: الشيخ حمود: عوضاً عن كل ذلك عمد رئيسا الجمهورية والحكومة إلى تأكيد عزمهما على إجراء مفاوضات مباشرة",
      "description": "لبنان: الشيخ حمود: عوضاً عن كل ذلك عمد رئيسا الجمهورية والحكومة إلى تأكيد عزمهما على إجراء مفاوضات مباشرة",
      "category": "political",
      "status": "confirmed",
      "source": "@almayadeen",
      "needsReview": false
    },
    {
      "id": "tg-almayadeen-364646",
      "time": "2026-04-10T19:20:37+00:00",
      "title": "لبنان: الشيخ حمود: كان على الحكومة أن تصرخ بأعلى الصوت بأنه عدوان على لبنان كل لبنان وليس على المقاومة",
      "description": "لبنان: الشيخ حمود: كان على الحكومة أن تصرخ بأعلى الصوت بأنه عدوان على لبنان كل لبنان وليس على المقاومة",
      "category": "statements",
      "status": "confirmed",
      "source": "@almayadeen",
      "needsReview": false
    },
    {
      "id": "tg-almayadeen-364645",
      "time": "2026-04-10T19:20:20+00:00",
      "title": "لبنان: الشيخ حمود: العدوان الإسرائيلي الآثم قدم يوم الأربعاء مادة قوية كان يمكن للحكومة وللحكم أن تعتمد عليها لتواجه العالم والوسطاء",
      "description": "لبنان: الشيخ حمود: العدوان الإسرائيلي الآثم قدم يوم الأربعاء مادة قوية كان يمكن للحكومة وللحكم أن تعتمد عليها لتواجه العالم والوسطاء",
      "category": "statements",
      "status": "confirmed",
      "source": "@almayadeen",
      "needsReview": false
    },
    {
      "id": "tg-almayadeen-364644",
      "time": "2026-04-10T19:19:55+00:00",
      "title": "لبنان: رئيس الاتحاد العالمي لعلماء المقاومة الشيخ ماهر حمود: كان على الحكومة أن ترتكز على نقاط القوة إثر وقف إطلاق النار الذي \"فُرض\" على الأميركي والصهيوني بصمود المقاومة",
      "description": "لبنان: رئيس الاتحاد العالمي لعلماء المقاومة الشيخ ماهر حمود: كان على الحكومة أن ترتكز على نقاط القوة إثر وقف إطلاق النار الذي \"فُرض\" على الأميركي والصهيوني بصمود المقاومة",
      "category": "statements",
      "status": "confirmed",
      "source": "@almayadeen",
      "needsReview": false
    },
    {
      "id": "tg-almayadeen-364643",
      "time": "2026-04-10T19:19:02+00:00",
      "title": "لبنان: شاكر البرجاوي للميادين: قرارات الحكومة اللبنانية تهدف إلى القضاء على المقاومة وهناك أفرقاء يسعون إلى تفكيك محور المقاومة",
      "description": "لبنان: شاكر البرجاوي للميادين: قرارات الحكومة اللبنانية تهدف إلى القضاء على المقاومة وهناك أفرقاء يسعون إلى تفكيك محور المقاومة",
      "category": "statements",
      "status": "confirmed",
      "source": "@almayadeen",
      "needsReview": false
    },
    {
      "id": "tg-unewschannel-319273",
      "time": "2026-04-10T19:17:34+00:00",
      "title": "الطيران الحربي الاسرائيلي يشن غارة على بلدة ديركيفا في قضاء صور",
      "description": "عاجل | الطيران الحربي الاسرائيلي يشن غارة على بلدة ديركيفا في قضاء صور",
      "category": "iran",
      "status": "developing",
      "source": "@unewschannel",
      "needsReview": false,
      "lat": 33.27,
      "lon": 35.2
    },
    {
      "id": "tg-almayadeen-364642",
      "time": "2026-04-10T19:16:29+00:00",
      "title": "لبنان: شاكر البرجاوي للميادين: هناك محاولة للإيحاء في الداخل اللبناني ولدى العدو الصهيوني أن وقف إطلاق النار هو بفضل التفاوض المباشر",
      "description": "لبنان: شاكر البرجاوي للميادين: هناك محاولة للإيحاء في الداخل اللبناني ولدى العدو الصهيوني أن وقف إطلاق النار هو بفضل التفاوض المباشر",
      "category": "statements",
      "status": "confirmed",
      "source": "@almayadeen",
      "needsReview": false
    },
    {
      "id": "tg-almayadeen-364641",
      "time": "2026-04-10T19:16:04+00:00",
      "title": "لبنان: شاكر البرجاوي للميادين: نرفض أي تفاوض مباشر مع العدو الصهيوني وهو لا يفهم إلا لغة القوة ونحن مع تطبيق القرار الدولي 1701",
      "description": "لبنان: شاكر البرجاوي للميادين: نرفض أي تفاوض مباشر مع العدو الصهيوني وهو لا يفهم إلا لغة القوة ونحن مع تطبيق القرار الدولي 1701",
      "category": "statements",
      "status": "confirmed",
      "source": "@almayadeen",
      "needsReview": false
    },
    {
      "id": "tg-unewschannel-319272",
      "time": "2026-04-10T19:15:12+00:00",
      "title": "الوكالة الوطنية للإعلام: الغارة التي شنّها العدو على بلدة صريفا في قضاء صور  استهدفت نقطة للهيئة الص",
      "description": "عاجل | الوكالة الوطنية للإعلام: الغارة التي شنّها العدو على بلدة صريفا في قضاء صور  استهدفت نقطة للهيئة الصحية الإسلامية وأوقعت اصابات",
      "category": "iran",
      "status": "developing",
      "source": "@unewschannel",
      "needsReview": false,
      "lat": 33.27,
      "lon": 35.2
    },
    {
      "id": "tg-unewschannel-319271",
      "time": "2026-04-10T19:13:01+00:00",
      "title": "المكتب الاعلامي لرئيس مجلس النواب اللبناني نبيه بري يجدد التأكيد بأنه \"الجهة الوحيدة المخولة التي يت",
      "description": "عاجل |  المكتب الاعلامي لرئيس مجلس النواب اللبناني نبيه بري يجدد التأكيد بأنه \"الجهة الوحيدة المخولة التي يتم من خلالها نشر مواقف الرئيس بري الرسمية علانية وليس عبر مصادر او زوار\"",
      "category": "iran",
      "status": "developing",
      "source": "@unewschannel",
      "needsReview": false
    },
    {
      "id": "tg-almayadeen-364640",
      "time": "2026-04-10T19:12:51+00:00",
      "title": "لبنان: شاكر البرجاوي للميادين: الحكومة اللبنانية حاولت الالتفاف على إنجازات المقاومة بالذهاب إلى المفاوضات المباشرة مع العدو",
      "description": "لبنان: شاكر البرجاوي للميادين: الحكومة اللبنانية حاولت الالتفاف على إنجازات المقاومة بالذهاب إلى المفاوضات المباشرة مع العدو",
      "category": "political",
      "status": "confirmed",
      "source": "@almayadeen",
      "needsReview": false
    },
    {
      "id": "tg-unewschannel-319270",
      "time": "2026-04-10T19:09:03+00:00",
      "title": "وزارة الصحة العامة في  في تحديث جديد لموجة اعتداءات الأربعاء 8 نيسان فقد ارتفعت الحصيلة إلى 357 شهيد",
      "description": "عاجل | وزارة الصحة العامة في  في تحديث جديد لموجة اعتداءات الأربعاء 8 نيسان فقد ارتفعت الحصيلة إلى 357 شهيدا و1223 جريحا  عاجل | وزارة الصحة العامة في  لا تزال هذه الحصيلة غير نهائية نظرا لاستمرار أعمال رفع الانقاض ووجود كمية كبيرة جدا من الاشلاء مما يتطلب وقتا لإنجاز فحوص الحمض النووي وتأكيد هويات",
      "category": "iran",
      "status": "developing",
      "source": "@unewschannel",
      "needsReview": false
    },
    {
      "id": "tg-unewschannel-319269",
      "time": "2026-04-10T19:08:36+00:00",
      "title": "وزارة الصحة العامة في  في تحديث جديد لموجة اعتداءات الأربعاء 8 نيسان فقد ارتفعت الحصيلة إلى 357 شهيد",
      "description": "عاجل | وزارة الصحة العامة في  في تحديث جديد لموجة اعتداءات الأربعاء 8 نيسان فقد ارتفعت الحصيلة إلى 357 شهيدا و1223 جريحا",
      "category": "iran",
      "status": "developing",
      "source": "@unewschannel",
      "needsReview": false
    },
    {
      "id": "tg-unewschannel-319268",
      "time": "2026-04-10T19:07:57+00:00",
      "title": "وزارة الصحة العامة في  الحصيلة الإجمالية للعدوان منذ 2 آذار حتى 10 نيسان إرتفعت إلى 1953 شهيدا و6303",
      "description": "عاجل | وزارة الصحة العامة في  الحصيلة الإجمالية للعدوان منذ 2 آذار حتى 10 نيسان إرتفعت إلى 1953 شهيدا و6303 جرحى",
      "category": "iran",
      "status": "developing",
      "source": "@unewschannel",
      "needsReview": false
    },
    {
      "id": "tg-unewschannel-319267",
      "time": "2026-04-10T19:03:37+00:00",
      "title": "المكتب الإعلامي في وزارة الصحة العامة في  ينفي صحة الصورة المتداولة عبر بعض مواقع التواصل الاجتماعي ",
      "description": "عاجل | المكتب الإعلامي في وزارة الصحة العامة في  ينفي صحة الصورة المتداولة عبر بعض مواقع التواصل الاجتماعي والتي تزعم تقديم وزير الصحة العامة استقالته من الحكومة",
      "category": "iran",
      "status": "developing",
      "source": "@unewschannel",
      "needsReview": false,
      "lat": 33.27,
      "lon": 35.2
    },
    {
      "id": "tg-mmirleb-14834",
      "time": "2026-04-10T19:03:18+00:00",
      "title": "⭕️أخرُجوا من جُحُورِكَم أيُّها الجُبَنَاء...",
      "description": "⭕️أخرُجوا من جُحُورِكَم أيُّها الجُبَنَاء...  جودة منخفضة ❤476🫡101🔥51👍7",
      "category": "hezbollah",
      "status": "confirmed",
      "source": "@mmirleb",
      "needsReview": false
    },
    {
      "id": "tg-mmirleb-14833",
      "time": "2026-04-10T19:03:16+00:00",
      "title": "⭕️أخرُجوا من جُحُورِكَم أيُّها الجُبَنَاء...",
      "description": "⭕️أخرُجوا من جُحُورِكَم أيُّها الجُبَنَاء...  جودة متوسطة ❤358🫡80🔥29👍8",
      "category": "hezbollah",
      "status": "confirmed",
      "source": "@mmirleb",
      "needsReview": false
    },
    {
      "id": "tg-unewschannel-319266",
      "time": "2026-04-10T19:00:33+00:00",
      "title": "المُقاومة الإسلاميّة في  تستهدف عند السّاعة 20:55 الجمعة 10-04-2026 مستوطنة أفيفيم للمرّة الثانية بص",
      "description": "عاجل | المُقاومة الإسلاميّة في  تستهدف عند السّاعة 20:55 الجمعة 10-04-2026 مستوطنة أفيفيم للمرّة الثانية بصليةٍ صاروخيّة",
      "category": "iran",
      "status": "developing",
      "source": "@unewschannel",
      "needsReview": false,
      "lat": 33.26,
      "lon": 35.5
    },
    {
      "id": "tg-mmirleb-14831",
      "time": "2026-04-10T18:58:15+00:00",
      "title": "⭕️أخرُجوا من جُحُورِكَم أيُّها الجُبَنَاء...",
      "description": "⭕️أخرُجوا من جُحُورِكَم أيُّها الجُبَنَاء...  جودة عالية ❤336🫡79🔥33👍7",
      "category": "hezbollah",
      "status": "confirmed",
      "source": "@mmirleb",
      "needsReview": false
    },
    {
      "id": "tg-unewschannel-319265",
      "time": "2026-04-10T18:47:20+00:00",
      "title": "المُقاومة الإسلاميّة في  تستهدف  عند السّاعة 20:15 الجمعة 10-04-2026 مستوطنة كريات شمونة بصليةٍ صارو",
      "description": "عاجل | المُقاومة الإسلاميّة في  تستهدف  عند السّاعة 20:15 الجمعة 10-04-2026 مستوطنة كريات شمونة بصليةٍ صاروخيّة",
      "category": "hezbollah",
      "status": "developing",
      "source": "@unewschannel",
      "needsReview": false,
      "lat": 33.21,
      "lon": 35.57
    },
    {
      "id": "tg-unewschannel-319264",
      "time": "2026-04-10T18:46:01+00:00",
      "title": "المُقاومة الإسلاميّة في  تستهدف عند السّاعة 20:10 الجمعة 10-04-2026 مستوطنة نهاريّا للمرّة الثانية ب",
      "description": "عاجل | المُقاومة الإسلاميّة في  تستهدف عند السّاعة 20:10 الجمعة 10-04-2026 مستوطنة نهاريّا للمرّة الثانية بصليةٍ صاروخيّة",
      "category": "iran",
      "status": "developing",
      "source": "@unewschannel",
      "needsReview": false
    },
    {
      "id": "tg-mmirleb-14829",
      "time": "2026-04-10T18:40:24+00:00",
      "title": "دفاعًا عن لبنان وشعبه، وردًّا على خرق العدوّ لاتفاق وقف إطلاق النار، واعتداءاته المتكرّرة على قرى ال",
      "description": "&rlm;  &rlm;&rlm;  دفاعًا عن لبنان وشعبه، وردًّا على خرق العدوّ لاتفاق وقف إطلاق النار، واعتداءاته المتكرّرة على قرى الجنوب، وبعدما التزمت المقاومة بوقف النار ولم يلتزم به العدوّ، استهدف مجاهدو المُقاومة الإسلاميّة عند السّاعة 20:55 الجمعة 10-04-2026 مستوطنة أفيفيم للمرّة الثانية بصليةٍ صاروخيّة. إن",
      "category": "hezbollah",
      "status": "confirmed",
      "source": "@mmirleb",
      "needsReview": false,
      "lat": 33.26,
      "lon": 35.5
    },
    {
      "id": "tg-unewschannel-319263",
      "time": "2026-04-10T18:37:08+00:00",
      "title": "المُقاومة الإسلاميّة في   تستهدف عند السّاعة 19:30 الجمعة 10-04-2026 تجمّعًا لآليات وجنود جيش العدوّ",
      "description": "عاجل | المُقاومة الإسلاميّة في   تستهدف عند السّاعة 19:30 الجمعة 10-04-2026 تجمّعًا لآليات وجنود جيش العدوّ الإسرائيليّ في محيط مدرسة الإشراق في مدينة بنت جبيل للمرّة الثالثة بصليةٍ صاروخيّة",
      "category": "hezbollah",
      "status": "developing",
      "source": "@unewschannel",
      "needsReview": false,
      "lat": 33.29,
      "lon": 35.42
    },
    {
      "id": "tg-mmirleb-14827",
      "time": "2026-04-10T18:30:38+00:00",
      "title": "دفاعًا عن لبنان وشعبه، وردًّا على خرق العدوّ لاتفاق وقف إطلاق النار، واعتداءاته المتكرّرة على قرى ال",
      "description": "&rlm;  &rlm;&rlm;  دفاعًا عن لبنان وشعبه، وردًّا على خرق العدوّ لاتفاق وقف إطلاق النار، واعتداءاته المتكرّرة على قرى الجنوب، وبعدما التزمت المقاومة بوقف النار ولم يلتزم به العدوّ، استهدف مجاهدو المُقاومة الإسلاميّة عند السّاعة 20:15 الجمعة 10-04-2026 مستوطنة كريات شمونة بصليةٍ صاروخيّة. إنّ هذا الرد",
      "category": "hezbollah",
      "status": "confirmed",
      "source": "@mmirleb",
      "needsReview": false,
      "lat": 33.21,
      "lon": 35.57
    },
    {
      "id": "tg-mmirleb-14836",
      "time": "2026-04-10T21:30:00.000+03:00",
      "title": "دفاعًا عن لبنان وشعبه، وردًّا على خرق العدوّ لاتفاق وقف إطلاق النار، واعتداءاته المتكرّرة على قرى ال",
      "description": "&rlm;  &rlm;&rlm;  دفاعًا عن لبنان وشعبه، وردًّا على خرق العدوّ لاتفاق وقف إطلاق النار، واعتداءاته المتكرّرة على قرى الجنوب، وبعدما التزمت المقاومة بوقف النار ولم يلتزم به العدوّ، استهدف مجاهدو المُقاومة الإسلاميّة منذ السّاعة 19:30 وحتى الساعة 21:30 الجمعة 10-04-2026 تجمّعات لآليات وجنود جيش العدوّ",
      "category": "hezbollah",
      "status": "confirmed",
      "source": "@mmirleb",
      "needsReview": false,
      "lat": 33.29,
      "lon": 35.42
    },
    {
      "id": "tg-mmirleb-14825",
      "time": "2026-04-10T18:20:35+00:00",
      "title": "دفاعًا عن لبنان وشعبه، وردًّا على خرق العدوّ لاتفاق وقف إطلاق النار واستهداف مبنى السراي الحكومي في",
      "description": "&rlm;  &rlm;&rlm;  دفاعًا عن لبنان وشعبه، وردًّا على خرق العدوّ لاتفاق وقف إطلاق النار واستهداف مبنى السراي الحكومي في مدينة النبطية، وبعدما التزمت المقاومة بوقف النار ولم يلتزم به العدوّ، استهدف مجاهدو المُقاومة الإسلاميّة عند السّاعة 20:10 الجمعة 10-04-2026 مستوطنة نهاريّا للمرّة الثانية بصليةٍ صا",
      "category": "hezbollah",
      "status": "confirmed",
      "source": "@mmirleb",
      "needsReview": false,
      "lat": 33.38,
      "lon": 35.49
    },
    {
      "id": "tg-mmirleb-14824",
      "time": "2026-04-10T18:20:03+00:00",
      "title": "دفاعًا عن لبنان وشعبه، وردًّا على خرق العدوّ لاتفاق وقف إطلاق النار، واعتداءاته المتكرّرة على قرى ال",
      "description": "&rlm;  &rlm;&rlm;  دفاعًا عن لبنان وشعبه، وردًّا على خرق العدوّ لاتفاق وقف إطلاق النار، واعتداءاته المتكرّرة على قرى الجنوب، وبعدما التزمت المقاومة بوقف النار ولم يلتزم به العدوّ، استهدف مجاهدو المُقاومة الإسلاميّة عند السّاعة 19:30 الجمعة 10-04-2026 تجمّعًا لآليات وجنود جيش العدوّ الإسرائيليّ في مح",
      "category": "hezbollah",
      "status": "confirmed",
      "source": "@mmirleb",
      "needsReview": false,
      "lat": 33.29,
      "lon": 35.42
    },
    {
      "id": "tg-unewschannel-319262",
      "time": "2026-04-10T18:13:04+00:00",
      "title": "صافرات الإنذار تدوي في الكريوت وعكا شمال  المحتلة",
      "description": "عاجل | صافرات الإنذار تدوي في الكريوت وعكا شمال  المحتلة",
      "category": "iran",
      "status": "developing",
      "source": "@unewschannel",
      "needsReview": false,
      "lat": 32.93,
      "lon": 35.08
    },
    {
      "id": "tg-unewschannel-319261",
      "time": "2026-04-10T18:11:10+00:00",
      "title": "حزب الله حول العدوان الصهيوني على السراي الحكومي في مدينة النبطية: ارتكب العدو الصهيوني اليوم مجزرة ",
      "description": "عاجل | حزب الله حول العدوان الصهيوني على السراي الحكومي في مدينة النبطية: ارتكب العدو الصهيوني اليوم مجزرة كبرى استكمالًا لمجزرته في يوم الأربعاء الأسود، مستهدفًا السراي الحكومي في مدينة النبطية، ما أدى إلى استشهاد ١٣ عنصرًا من جهاز أمن الدولة، في اعتداء سافر…  عاجل | حزب الله: ندعو السلطة  إلى أن ت",
      "category": "hezbollah",
      "status": "developing",
      "source": "@unewschannel",
      "needsReview": false,
      "lat": 33.38,
      "lon": 35.49
    },
    {
      "id": "tg-unewschannel-319260",
      "time": "2026-04-10T18:11:05+00:00",
      "title": "حزب الله حول العدوان الصهيوني على السراي الحكومي في مدينة النبطية: ارتكب العدو الصهيوني اليوم مجزرة ",
      "description": "عاجل | حزب الله حول العدوان الصهيوني على السراي الحكومي في مدينة النبطية: ارتكب العدو الصهيوني اليوم مجزرة كبرى استكمالًا لمجزرته في يوم الأربعاء الأسود، مستهدفًا السراي الحكومي في مدينة النبطية، ما أدى إلى استشهاد ١٣ عنصرًا من جهاز أمن الدولة، في اعتداء سافر…  عاجل | حزب الله: ندعو السلطة  إلى أن ت",
      "category": "hezbollah",
      "status": "developing",
      "source": "@unewschannel",
      "needsReview": false,
      "lat": 33.38,
      "lon": 35.49
    },
    {
      "id": "tg-unewschannel-319259",
      "time": "2026-04-10T18:10:15+00:00",
      "title": "حزب الله حول العدوان الصهيوني على السراي الحكومي في مدينة النبطية: ارتكب العدو الصهيوني اليوم مجزرة ",
      "description": "عاجل | حزب الله حول العدوان الصهيوني على السراي الحكومي في مدينة النبطية: ارتكب العدو الصهيوني اليوم مجزرة كبرى استكمالًا لمجزرته في يوم الأربعاء الأسود، مستهدفًا السراي الحكومي في مدينة النبطية، ما أدى إلى استشهاد ١٣ عنصرًا من جهاز أمن الدولة، في اعتداء سافر…  عاجل | حزب الله: ندين هذه المجزرة الوح",
      "category": "hezbollah",
      "status": "developing",
      "source": "@unewschannel",
      "needsReview": false,
      "lat": 33.38,
      "lon": 35.49
    },
    {
      "id": "tg-unewschannel-319258",
      "time": "2026-04-10T18:09:24+00:00",
      "title": "حزب الله حول العدوان الصهيوني على السراي الحكومي في مدينة النبطية: ارتكب العدو الصهيوني اليوم مجزرة ",
      "description": "عاجل | حزب الله حول العدوان الصهيوني على السراي الحكومي في مدينة النبطية: ارتكب العدو الصهيوني اليوم مجزرة كبرى استكمالًا لمجزرته في يوم الأربعاء الأسود، مستهدفًا السراي الحكومي في مدينة النبطية، ما أدى إلى استشهاد ١٣ عنصرًا من جهاز أمن الدولة، في اعتداء سافر…  عاجل | حزب الله: إزاء كل التنازلات الت",
      "category": "hezbollah",
      "status": "developing",
      "source": "@unewschannel",
      "needsReview": false,
      "lat": 33.38,
      "lon": 35.49
    },
    {
      "id": "tg-unewschannel-319257",
      "time": "2026-04-10T18:08:33+00:00",
      "title": "حزب الله حول العدوان الصهيوني على السراي الحكومي في مدينة النبطية: ارتكب العدو الصهيوني اليوم مجزرة ",
      "description": "عاجل | حزب الله حول العدوان الصهيوني على السراي الحكومي في مدينة النبطية: ارتكب العدو الصهيوني اليوم مجزرة كبرى استكمالًا لمجزرته في يوم الأربعاء الأسود، مستهدفًا السراي الحكومي في مدينة النبطية، ما أدى إلى استشهاد ١٣ عنصرًا من جهاز أمن الدولة، في اعتداء سافر…  عاجل | حزب الله: إن هذا العدوان الإجرا",
      "category": "hezbollah",
      "status": "developing",
      "source": "@unewschannel",
      "needsReview": false,
      "lat": 33.38,
      "lon": 35.49
    },
    {
      "id": "tg-unewschannel-319256",
      "time": "2026-04-10T18:06:09+00:00",
      "title": "حزب الله حول العدوان الصهيوني على السراي الحكومي في مدينة النبطية: ارتكب العدو الصهيوني اليوم مجزرة ",
      "description": "عاجل | حزب الله حول العدوان الصهيوني على السراي الحكومي في مدينة النبطية: ارتكب العدو الصهيوني اليوم مجزرة كبرى استكمالًا لمجزرته في يوم الأربعاء الأسود، مستهدفًا السراي الحكومي في مدينة النبطية، ما أدى إلى استشهاد ١٣ عنصرًا من جهاز أمن الدولة، في اعتداء سافر وخطير طاول مؤسسة أمنية رسمية سيادية، مما",
      "category": "hezbollah",
      "status": "developing",
      "source": "@unewschannel",
      "needsReview": false,
      "lat": 33.38,
      "lon": 35.49
    },
    {
      "id": "tg-unewschannel-319255",
      "time": "2026-04-10T17:57:55+00:00",
      "title": "يونيوز:  حزب الله ابلغ الوسطاء رفضه منح إسرائيل حرية التحرك العسكري في لبنان مشددا على الرد على أي ا",
      "description": "عاجل | يونيوز:  حزب الله ابلغ الوسطاء رفضه منح إسرائيل حرية التحرك العسكري في لبنان مشددا على الرد على أي اعتداء ورفض العودة إلى آليات المرحلة السابقة",
      "category": "hezbollah",
      "status": "developing",
      "source": "@unewschannel",
      "needsReview": false
    },
    {
      "id": "tg-almayadeen-364590",
      "time": "2026-04-10T17:26:12+00:00",
      "title": "لبنان: المقاومة الإسلامية: استهدفنا قاعدة \"شراغا\" (المقر الإداري لقيادة لواء غولاني) شمال مدينة عكّا المحتلة بصلية صاروخية وسرب من المسيّرات الانقضاضية",
      "description": "لبنان: المقاومة الإسلامية: استهدفنا قاعدة \"شراغا\" (المقر الإداري لقيادة لواء غولاني) شمال مدينة عكّا المحتلة بصلية صاروخية وسرب من المسيّرات الانقضاضية",
      "category": "hezbollah",
      "status": "confirmed",
      "source": "@almayadeen",
      "needsReview": false
    },
    {
      "id": "tg-unewschannel-319247",
      "time": "2026-04-10T17:25:47+00:00",
      "title": "المُقاومة الإسلاميّة في  تستهدف عند السّاعة 18:00 الجمعة 10-04-2026 قاعدة شراغا (المقر الإداري لقياد",
      "description": "عاجل | المُقاومة الإسلاميّة في  تستهدف عند السّاعة 18:00 الجمعة 10-04-2026 قاعدة شراغا (المقر الإداري لقيادة لواء غولاني) شمال مدينة عكّا المُحتلّة بصليةٍ صاروخيّة وسربٍ من المسيّرات الانقضاضيّة",
      "category": "hezbollah",
      "status": "developing",
      "source": "@unewschannel",
      "needsReview": false
    },
    {
      "id": "tg-mmirleb-14822",
      "time": "2026-04-10T17:25:18+00:00",
      "title": "بيان صادر عن حزب الله حول العدوان الصهيوني على السراي الحكومي في مدينة النبطية:",
      "description": "بيان صادر عن حزب الله حول العدوان الصهيوني على السراي الحكومي في مدينة النبطية:  ارتكب العدو الصهيوني اليوم مجزرة كبرى استكمالًا لمجزرته في يوم الأربعاء الأسود، مستهدفًا السراي الحكومي في مدينة النبطية، ما أدى إلى استشهاد ١٣ عنصرًا من جهاز أمن الدولة، في اعتداء سافر وخطير طاول مؤسسة أمنية رسمية سياد",
      "category": "hezbollah",
      "status": "confirmed",
      "source": "@mmirleb",
      "needsReview": false,
      "lat": 33.38,
      "lon": 35.49
    },
    {
      "id": "tg-mmirleb-14821",
      "time": "2026-04-10T17:25:03+00:00",
      "title": "دفاعًا عن لبنان وشعبه، وردًّا على خرق العدوّ لاتفاق وقف إطلاق النار، واعتداءاته المتكرّرة على مدينة",
      "description": "&rlm;  &rlm;&rlm;  دفاعًا عن لبنان وشعبه، وردًّا على خرق العدوّ لاتفاق وقف إطلاق النار، واعتداءاته المتكرّرة على مدينة صور، وبعدما التزمت المقاومة بوقف النار ولم يلتزم به العدوّ، استهدف مجاهدو المُقاومة الإسلاميّة عند السّاعة 18:00 الجمعة 10-04-2026 قاعدة شراغا (المقر الإداري لقيادة لواء غولاني) شما",
      "category": "hezbollah",
      "status": "confirmed",
      "source": "@mmirleb",
      "needsReview": false,
      "lat": 33.27,
      "lon": 35.2
    },
    {
      "id": "tg-unewschannel-319246",
      "time": "2026-04-10T17:24:07+00:00",
      "title": "القناة 12 العبرية: تقرير أولي عن سقوط صاروخ في كريات شمونه دون دوي صفارات الإنذار",
      "description": "القناة 12 العبرية: تقرير أولي عن سقوط صاروخ في كريات شمونه دون دوي صفارات الإنذار 🔥1",
      "category": "iran",
      "status": "confirmed",
      "source": "@unewschannel",
      "needsReview": false
    },
    {
      "id": "tg-almayadeen-364589",
      "time": "2026-04-10T17:22:47+00:00",
      "title": "وسائل إعلام إسرائيلية: تقرير أولي عن سقوط صاروخ في \"كريات شمونة\" من دون دوي صفارات الإنذار",
      "description": "وسائل إعلام إسرائيلية: تقرير أولي عن سقوط صاروخ في \"كريات شمونة\" من دون دوي صفارات الإنذار",
      "category": "hezbollah",
      "status": "confirmed",
      "source": "@almayadeen",
      "needsReview": false,
      "lat": 33.21,
      "lon": 35.57
    },
    {
      "id": "tg-unewschannel-319245",
      "time": "2026-04-10T17:20:37+00:00",
      "title": "الطائرات الحربية الاسرائيلية تشنّ غارةً بصاروخين على منطقة المشاع بين المنصوري ومجدل زون في قضاء صور",
      "description": "عاجل | الطائرات الحربية الاسرائيلية تشنّ غارةً بصاروخين على منطقة المشاع بين المنصوري ومجدل زون في قضاء صور  ❤1",
      "category": "iran",
      "status": "developing",
      "source": "@unewschannel",
      "needsReview": false,
      "lat": 33.27,
      "lon": 35.2
    },
    {
      "id": "tg-almayadeen-364588",
      "time": "2026-04-10T17:17:12+00:00",
      "title": "وسائل إعلام إسرائيلية: صفارات الإنذار تدوي في \"نهاريا\" ومحيطها",
      "description": "وسائل إعلام إسرائيلية: صفارات الإنذار تدوي في \"نهاريا\" ومحيطها",
      "category": "statements",
      "status": "confirmed",
      "source": "@almayadeen",
      "needsReview": false,
      "lat": 33,
      "lon": 35.09
    },
    {
      "id": "tg-almayadeen-364587",
      "time": "2026-04-10T17:16:46+00:00",
      "title": "لبنان: مراسل الميادين في الجنوب: صلية صاروخية انطلقت من جنوب لبنان قبل قليل وصفارات الإنذار تدوي في الشريط الساحلي للجليل الغربي",
      "description": "لبنان: مراسل الميادين في الجنوب: صلية صاروخية انطلقت من جنوب لبنان قبل قليل وصفارات الإنذار تدوي في الشريط الساحلي للجليل الغربي",
      "category": "hezbollah",
      "status": "confirmed",
      "source": "@almayadeen",
      "needsReview": false,
      "lat": 33.28,
      "lon": 35.4
    },
    {
      "id": "tg-almayadeen-364586",
      "time": "2026-04-10T17:12:36+00:00",
      "title": "لبنان: مراسل الميادين في الجنوب: غارة من مسيرة إسرائيلية استهدفت سيارة على طريق عدشيت - القصيبة",
      "description": "لبنان: مراسل الميادين في الجنوب: غارة من مسيرة إسرائيلية استهدفت سيارة على طريق عدشيت - القصيبة",
      "category": "statements",
      "status": "confirmed",
      "source": "@almayadeen",
      "needsReview": false,
      "lat": 33.26,
      "lon": 35.35
    },
    {
      "id": "tg-unewschannel-319244",
      "time": "2026-04-10T17:10:48+00:00",
      "title": "الطيران الحربي الاسرائيلي يشنّ غارتين على المحمودية قرب العيشية بمنطقة جزين",
      "description": "عاجل | الطيران الحربي الاسرائيلي يشنّ غارتين على المحمودية قرب العيشية بمنطقة جزين",
      "category": "iran",
      "status": "developing",
      "source": "@unewschannel",
      "needsReview": false
    },
    {
      "id": "tg-almayadeen-364585",
      "time": "2026-04-10T17:06:25+00:00",
      "title": "لبنان: المقاومة الإسلامية: استهدفنا مستوطنة \"يرؤون\" بصلية صاروخيّة",
      "description": "لبنان: المقاومة الإسلامية: استهدفنا مستوطنة \"يرؤون\" بصلية صاروخيّة",
      "category": "hezbollah",
      "status": "confirmed",
      "source": "@almayadeen",
      "needsReview": false
    },
    {
      "id": "tg-unewschannel-319243",
      "time": "2026-04-10T17:01:37+00:00",
      "title": "المُقاومة الإسلاميّة في  تستهدف عند السّاعة 19:30 الجمعة 10-04-2026 مستوطنة يرؤون بصليةٍ صاروخيّة",
      "description": "عاجل | المُقاومة الإسلاميّة في  تستهدف عند السّاعة 19:30 الجمعة 10-04-2026 مستوطنة يرؤون بصليةٍ صاروخيّة",
      "category": "iran",
      "status": "developing",
      "source": "@unewschannel",
      "needsReview": false
    },
    {
      "id": "tg-mmirleb-14820",
      "time": "2026-04-10T17:00:21+00:00",
      "title": "دفاعًا عن لبنان وشعبه، وردًّا على خرق العدوّ لاتفاق وقف إطلاق النار، واعتداءاته المتكرّرة على مدينة",
      "description": "&rlm;  &rlm;&rlm;  دفاعًا عن لبنان وشعبه، وردًّا على خرق العدوّ لاتفاق وقف إطلاق النار، واعتداءاته المتكرّرة على مدينة صور، وبعدما التزمت المقاومة بوقف النار ولم يلتزم به العدوّ، استهدف مجاهدو المُقاومة الإسلاميّة عند السّاعة 18:00 الجمعة 10-04-2026 قاعدة شراغا (المقر الإداري لقيادة لواء غولاني) شما",
      "category": "hezbollah",
      "status": "confirmed",
      "source": "@mmirleb",
      "needsReview": false,
      "lat": 33.27,
      "lon": 35.2
    },
    {
      "id": "tg-almayadeen-364584",
      "time": "2026-04-10T16:59:44+00:00",
      "title": "لبنان: مراسل الميادين في بيروت: رئيس الحكومة اللبنانية يلتقي الأمين العام للأمم المتحدة في نيويورك الثلاثاء قبل أن ينتقل إلى واشنطن",
      "description": "لبنان: مراسل الميادين في بيروت: رئيس الحكومة اللبنانية يلتقي الأمين العام للأمم المتحدة في نيويورك الثلاثاء قبل أن ينتقل إلى واشنطن",
      "category": "statements",
      "status": "confirmed",
      "source": "@almayadeen",
      "needsReview": false,
      "lat": 33.89,
      "lon": 35.51
    },
    {
      "id": "tg-unewschannel-319242",
      "time": "2026-04-10T16:59:28+00:00",
      "title": "المُقاومة الإسلاميّة في  تستهدف عند السّاعة 19:00 الجمعة 10-04-2026 تجمّعًا لجنود جيش العدوّ الإسرائ",
      "description": "عاجل | المُقاومة الإسلاميّة في  تستهدف عند السّاعة 19:00 الجمعة 10-04-2026 تجمّعًا لجنود جيش العدوّ الإسرائيليّ عند تلّة العويضة في بلدة العديسة الحدوديّة بمسيّرة انقضاضيّة، وتحقق إصابة مباشرة",
      "category": "iran",
      "status": "developing",
      "source": "@unewschannel",
      "needsReview": false,
      "lat": 33.34,
      "lon": 35.51
    },
    {
      "id": "tg-almayadeen-364583",
      "time": "2026-04-10T16:54:44+00:00",
      "title": "إيران: السيد مجتبى خامنئي: استشهاد الدكتور خرازي وثيقة فخر للمجتمع الجامعي والأساتذة والمسؤولين السياسيين في الجمهورية الإسلامية",
      "description": "إيران: السيد مجتبى خامنئي: استشهاد الدكتور خرازي وثيقة فخر للمجتمع الجامعي والأساتذة والمسؤولين السياسيين في الجمهورية الإسلامية",
      "category": "iran",
      "status": "confirmed",
      "source": "@almayadeen",
      "needsReview": false
    },
    {
      "id": "tg-almayadeen-364582",
      "time": "2026-04-10T16:53:45+00:00",
      "title": "إيران: السيد مجتبى خامنئي: استشهاد خرازي وثيقة عار تثبت دناءة المستكبرين الأميركيين والصهاينة وأعداء العلم والحضارة الإيرانية",
      "description": "إيران: السيد مجتبى خامنئي: استشهاد خرازي وثيقة عار تثبت دناءة المستكبرين الأميركيين والصهاينة وأعداء العلم والحضارة الإيرانية",
      "category": "iran",
      "status": "confirmed",
      "source": "@almayadeen",
      "needsReview": false
    },
    {
      "id": "tg-almayadeen-364581",
      "time": "2026-04-10T16:51:30+00:00",
      "title": "إيران: قائد الثورة والجمهورية السيد مجتبى خامنئي يعزي ويبارك باستشهاد رئيس المجلس الاستراتيجي للعلاقات الخارجية كمال خرازي",
      "description": "إيران: قائد الثورة والجمهورية السيد مجتبى خامنئي يعزي ويبارك باستشهاد رئيس المجلس الاستراتيجي للعلاقات الخارجية كمال خرازي",
      "category": "iran",
      "status": "confirmed",
      "source": "@almayadeen",
      "needsReview": false
    },
    {
      "id": "tg-unewschannel-319241",
      "time": "2026-04-10T16:51:17+00:00",
      "title": "المُقاومة الإسلاميّة في  تستهدف عند السّاعة 18:45 الجمعة 10-04-2026 بنى تحتيّة تتبع لجيش العدوّ الإس",
      "description": "عاجل | المُقاومة الإسلاميّة في  تستهدف عند السّاعة 18:45 الجمعة 10-04-2026 بنى تحتيّة تتبع لجيش العدوّ الإسرائيليّ في مستوطنة كرميئيل للمرّة الثانية بصليةٍ صاروخيّة",
      "category": "iran",
      "status": "developing",
      "source": "@unewschannel",
      "needsReview": false
    },
    {
      "id": "tg-unewschannel-319240",
      "time": "2026-04-10T16:49:50+00:00",
      "title": "المُقاومة الإسلاميّة في  تستهدف عند السّاعة 18:15 الجمعة 10-04-2026 ثكنة كريات شمونة وقاعدة بيت هلل ",
      "description": "عاجل | المُقاومة الإسلاميّة في  تستهدف عند السّاعة 18:15 الجمعة 10-04-2026 ثكنة كريات شمونة وقاعدة بيت هلل بأسرابٍ من المُسيّرات الانقضاضيّة",
      "category": "hezbollah",
      "status": "developing",
      "source": "@unewschannel",
      "needsReview": false,
      "lat": 33.21,
      "lon": 35.57
    },
    {
      "id": "tg-unewschannel-319239",
      "time": "2026-04-10T16:48:34+00:00",
      "title": "المُقاومة الإسلاميّة في  تستهدف عند السّاعة 18:15 الجمعة 10-04-2026 تجمّعًا لآليات وجنود جيش العدوّ ",
      "description": "عاجل | المُقاومة الإسلاميّة في  تستهدف عند السّاعة 18:15 الجمعة 10-04-2026 تجمّعًا لآليات وجنود جيش العدوّ الإسرائيليّ في محيط مدرسة الإشراق في مدينة بنت جبيل للمرّة الثانية بصليةٍ صاروخيّة",
      "category": "hezbollah",
      "status": "developing",
      "source": "@unewschannel",
      "needsReview": false,
      "lat": 33.29,
      "lon": 35.42
    },
    {
      "id": "tg-almayadeen-364580",
      "time": "2026-04-10T16:43:15+00:00",
      "title": "وسائل إعلام إسرائيلية: صفارات الإنذار تدوي في \"يرؤون\" بالجليل الغربي",
      "description": "وسائل إعلام إسرائيلية: صفارات الإنذار تدوي في \"يرؤون\" بالجليل الغربي",
      "category": "hezbollah",
      "status": "confirmed",
      "source": "@almayadeen",
      "needsReview": false,
      "lat": 33.05,
      "lon": 35.4
    },
    {
      "id": "tg-almayadeen-364579",
      "time": "2026-04-10T16:41:18+00:00",
      "title": "لبنان: مراسل الميادين في الجنوب: استهدافات المقاومة توسعت اليوم وإحداها طالت قاعدة بحرية للاحتلال تبعد 160 كلم عن الحدود",
      "description": "لبنان: مراسل الميادين في الجنوب: استهدافات المقاومة توسعت اليوم وإحداها طالت قاعدة بحرية للاحتلال تبعد 160 كلم عن الحدود",
      "category": "statements",
      "status": "confirmed",
      "source": "@almayadeen",
      "needsReview": false
    },
    {
      "id": "tg-almayadeen-364578",
      "time": "2026-04-10T16:35:09+00:00",
      "title": "لبنان: رئاسة البرلمان اللبناني: هيبت الحلبوسي جدد لبري دعم العراق للبنان على مختلف المستويات لمواجهة التداعيات الناجمة عن العدوان الإسرائيلي خصوصاً ملف النازحين",
      "description": "لبنان: رئاسة البرلمان اللبناني: هيبت الحلبوسي جدد لبري دعم العراق للبنان على مختلف المستويات لمواجهة التداعيات الناجمة عن العدوان الإسرائيلي خصوصاً ملف النازحين",
      "category": "statements",
      "status": "confirmed",
      "source": "@almayadeen",
      "needsReview": false
    },
    {
      "id": "tg-almayadeen-364577",
      "time": "2026-04-10T16:33:27+00:00",
      "title": "لبنان: رئاسة البرلمان اللبناني: الرئيس نبيه بري بحث من نظيره العراقي هيبت الحلبوسي التطورات في المنطقة والعدوان الإسرائيلي على لبنان",
      "description": "لبنان: رئاسة البرلمان اللبناني: الرئيس نبيه بري بحث من نظيره العراقي هيبت الحلبوسي التطورات في المنطقة والعدوان الإسرائيلي على لبنان",
      "category": "statements",
      "status": "confirmed",
      "source": "@almayadeen",
      "needsReview": false
    },
    {
      "id": "tg-almayadeen-364576",
      "time": "2026-04-10T16:31:06+00:00",
      "title": "لبنان: المقاومة الإسلامية: استهدفنا تجمّعاً لجنود \"جيش\" العدو الإسرائيلي عند تلّة العويضة في بلدة العديسة الحدودية بمسيرة انقضاضية، وحققنا إصابة مباشرة",
      "description": "لبنان: المقاومة الإسلامية: استهدفنا تجمّعاً لجنود \"جيش\" العدو الإسرائيلي عند تلّة العويضة في بلدة العديسة الحدودية بمسيرة انقضاضية، وحققنا إصابة مباشرة",
      "category": "hezbollah",
      "status": "confirmed",
      "source": "@almayadeen",
      "needsReview": false,
      "lat": 33.34,
      "lon": 35.51
    },
    {
      "id": "tg-almayadeen-364575",
      "time": "2026-04-10T16:29:55+00:00",
      "title": "لبنان: المقاومة الإسلامية: استهداف \"كرميئيل\" يأتي دفاعاً عن لبنان وشعبه ورداً على اعتداءات العدو الإسرائيلي المتكررة على مدينة صور",
      "description": "لبنان: المقاومة الإسلامية: استهداف \"كرميئيل\" يأتي دفاعاً عن لبنان وشعبه ورداً على اعتداءات العدو الإسرائيلي المتكررة على مدينة صور",
      "category": "hezbollah",
      "status": "confirmed",
      "source": "@almayadeen",
      "needsReview": false,
      "lat": 33.27,
      "lon": 35.2
    },
    {
      "id": "tg-mmirleb-14818",
      "time": "2026-04-10T16:29:37+00:00",
      "title": "دفاعًا عن لبنان وشعبه، وردًّا على خرق العدوّ لاتفاق وقف إطلاق النار، واعتداءاته المتكرّرة على قرى ال",
      "description": "&rlm;  &rlm;&rlm;  دفاعًا عن لبنان وشعبه، وردًّا على خرق العدوّ لاتفاق وقف إطلاق النار، واعتداءاته المتكرّرة على قرى الجنوب، وبعدما التزمت المقاومة بوقف النار ولم يلتزم به العدوّ، استهدف مجاهدو المُقاومة الإسلاميّة عند السّاعة 19:30 الجمعة 10-04-2026 مستوطنة يرؤون بصليةٍ صاروخيّة. إنّ هذا الردّ سيست",
      "category": "hezbollah",
      "status": "confirmed",
      "source": "@mmirleb",
      "needsReview": false
    },
    {
      "id": "tg-almayadeen-364574",
      "time": "2026-04-10T16:28:30+00:00",
      "title": "لبنان: المقاومة الإسلامية: استهدفنا بنى تحتية للعدو الإسرائيلي في مستوطنة \"كرميئيل\" للمرة الثانية بصلية صاروخية",
      "description": "لبنان: المقاومة الإسلامية: استهدفنا بنى تحتية للعدو الإسرائيلي في مستوطنة \"كرميئيل\" للمرة الثانية بصلية صاروخية",
      "category": "hezbollah",
      "status": "confirmed",
      "source": "@almayadeen",
      "needsReview": false
    },
    {
      "id": "tg-almayadeen-364573",
      "time": "2026-04-10T16:27:47+00:00",
      "title": "تونس: مير مسعود حسينيان للميادين: الأمن لا يتجزأ لذلك أدرجت إيران وقف إطلاق النار في لبنان والمنطقة ضمن شروط بدء المفاوضات",
      "description": "تونس: مير مسعود حسينيان للميادين: الأمن لا يتجزأ لذلك أدرجت إيران وقف إطلاق النار في لبنان والمنطقة ضمن شروط بدء المفاوضات",
      "category": "iran",
      "status": "confirmed",
      "source": "@almayadeen",
      "needsReview": false
    },
    {
      "id": "tg-almayadeen-364572",
      "time": "2026-04-10T16:27:29+00:00",
      "title": "تونس: مير مسعود حسينيان للميادين: العلاقات دول الجوار كانت جيدة قبل دخول الطرف الأميركي إلى المنطقة",
      "description": "تونس: مير مسعود حسينيان للميادين: العلاقات دول الجوار كانت جيدة قبل دخول الطرف الأميركي إلى المنطقة",
      "category": "statements",
      "status": "confirmed",
      "source": "@almayadeen",
      "needsReview": false
    },
    {
      "id": "tg-almayadeen-364571",
      "time": "2026-04-10T16:27:13+00:00",
      "title": "تونس: مير مسعود حسينيان للميادين: واثقون من عودة العلاقات الجيدة مع دول الجوار إلى سابق عهدها مع زوال أسباب فتورها الأخير",
      "description": "تونس: مير مسعود حسينيان للميادين: واثقون من عودة العلاقات الجيدة مع دول الجوار إلى سابق عهدها مع زوال أسباب فتورها الأخير",
      "category": "statements",
      "status": "confirmed",
      "source": "@almayadeen",
      "needsReview": false
    },
    {
      "id": "tg-mmirleb-14816",
      "time": "2026-04-10T16:25:37+00:00",
      "title": "دفاعًا عن لبنان وشعبه، وردًّا على خرق العدوّ لاتفاق وقف إطلاق النار، واعتداءاته المتكرّرة على قرى ال",
      "description": "&rlm;  &rlm;&rlm;  دفاعًا عن لبنان وشعبه، وردًّا على خرق العدوّ لاتفاق وقف إطلاق النار، واعتداءاته المتكرّرة على قرى الجنوب، وبعدما التزمت المقاومة بوقف النار ولم يلتزم به العدوّ، استهدف مجاهدو المُقاومة الإسلاميّة عند السّاعة 19:00 الجمعة 10-04-2026 تجمّعًا لجنود جيش العدوّ الإسرائيليّ عند تلّة الع",
      "category": "hezbollah",
      "status": "confirmed",
      "source": "@mmirleb",
      "needsReview": false,
      "lat": 33.34,
      "lon": 35.51
    },
    {
      "id": "tg-mmirleb-14814",
      "time": "2026-04-10T16:21:01+00:00",
      "title": "دفاعًا عن لبنان وشعبه، وردًّا على خرق العدوّ لاتفاق وقف إطلاق النار، واعتداءاته المتكرّرة على مدينة",
      "description": "&rlm;  &rlm;&rlm;  دفاعًا عن لبنان وشعبه، وردًّا على خرق العدوّ لاتفاق وقف إطلاق النار، واعتداءاته المتكرّرة على مدينة صور، وبعدما التزمت المقاومة بوقف النار ولم يلتزم به العدوّ، استهدف مجاهدو المُقاومة الإسلاميّة عند السّاعة 18:45 الجمعة 10-04-2026 بنى تحتيّة تتبع لجيش العدوّ الإسرائيليّ في مستوطنة",
      "category": "hezbollah",
      "status": "confirmed",
      "source": "@mmirleb",
      "needsReview": false,
      "lat": 33.27,
      "lon": 35.2
    },
    {
      "id": "tg-unewschannel-319238",
      "time": "2026-04-10T16:16:38+00:00",
      "title": "الجبهة الداخلية الإسرائيلية: صافرات الإنذار تدوي في كرميئيل ومحيطها في الجليل الأعلى إثر إطلاق صواري",
      "description": "عاجل | الجبهة الداخلية الإسرائيلية: صافرات الإنذار تدوي في كرميئيل ومحيطها في الجليل الأعلى إثر إطلاق صواريخ من  🔥1",
      "category": "hezbollah",
      "status": "developing",
      "source": "@unewschannel",
      "needsReview": false,
      "lat": 33.05,
      "lon": 35.4
    },
    {
      "id": "tg-mmirleb-14812",
      "time": "2026-04-10T16:10:15+00:00",
      "title": "دفاعًا عن لبنان وشعبه، وردًّا على خرق العدوّ لاتفاق وقف إطلاق النار، واعتداءاته المتكرّرة على قرى ال",
      "description": "&rlm;  &rlm;&rlm;  دفاعًا عن لبنان وشعبه، وردًّا على خرق العدوّ لاتفاق وقف إطلاق النار، واعتداءاته المتكرّرة على قرى الجنوب، وبعدما التزمت المقاومة بوقف النار ولم يلتزم به العدوّ، استهدف مجاهدو المُقاومة الإسلاميّة عند السّاعة 18:15 الجمعة 10-04-2026 ثكنة كريات شمونة وقاعدة بيت هلل بأسرابٍ من المُسي",
      "category": "hezbollah",
      "status": "confirmed",
      "source": "@mmirleb",
      "needsReview": false,
      "lat": 33.21,
      "lon": 35.57
    },
    {
      "id": "tg-unewschannel-319236",
      "time": "2026-04-10T16:05:31+00:00",
      "title": "المُقاومة الإسلاميّة في  تستهدف عند السّاعة 16:40 الجمعة 10-04-2026 تجمّعًا لآليات وجنود جيش العدوّ ",
      "description": "عاجل | المُقاومة الإسلاميّة في  تستهدف عند السّاعة 16:40 الجمعة 10-04-2026 تجمّعًا لآليات وجنود جيش العدوّ الإسرائيليّ في محيط مدرسة الإشراق في مدينة بنت جبيل بصليةٍ صاروخيّة 🔥1",
      "category": "hezbollah",
      "status": "developing",
      "source": "@unewschannel",
      "needsReview": false,
      "lat": 33.29,
      "lon": 35.42
    },
    {
      "id": "tg-mmirleb-14810",
      "time": "2026-04-10T16:00:25+00:00",
      "title": "دفاعًا عن لبنان وشعبه، وردًّا على خرق العدوّ لاتفاق وقف إطلاق النار، واعتداءاته المتكرّرة على قرى ال",
      "description": "&rlm;  &rlm;&rlm;  دفاعًا عن لبنان وشعبه، وردًّا على خرق العدوّ لاتفاق وقف إطلاق النار، واعتداءاته المتكرّرة على قرى الجنوب، وبعدما التزمت المقاومة بوقف النار ولم يلتزم به العدوّ، استهدف مجاهدو المُقاومة الإسلاميّة عند السّاعة 18:15 الجمعة 10-04-2026 تجمّعًا لآليات وجنود جيش العدوّ الإسرائيليّ في مح",
      "category": "hezbollah",
      "status": "confirmed",
      "source": "@mmirleb",
      "needsReview": false,
      "lat": 33.29,
      "lon": 35.42
    },
    {
      "id": "tg-unewschannel-319235",
      "time": "2026-04-10T15:52:43+00:00",
      "title": "المُقاومة الإسلاميّة في  تستهدف عند السّاعة 18:00 الجمعة 10-04-2026 مستوطنتي ليمان وشلومي بصلياتٍ صا",
      "description": "عاجل | المُقاومة الإسلاميّة في  تستهدف عند السّاعة 18:00 الجمعة 10-04-2026 مستوطنتي ليمان وشلومي بصلياتٍ صاروخيّة",
      "category": "hezbollah",
      "status": "developing",
      "source": "@unewschannel",
      "needsReview": false,
      "lat": 33.07,
      "lon": 35.15
    },
    {
      "id": "tg-unewschannel-319234",
      "time": "2026-04-10T15:51:55+00:00",
      "title": "وزير الخارجية الايراني خلال اتصال هاتفي مع السفير الإيراني المقترح لدى  رؤوف شيباني يؤكد شمول  تفاهم",
      "description": "عاجل | وزير الخارجية الايراني خلال اتصال هاتفي مع السفير الإيراني المقترح لدى  رؤوف شيباني يؤكد شمول  تفاهم إطلاق النار بين إيران وأميركا",
      "category": "iran",
      "status": "developing",
      "source": "@unewschannel",
      "needsReview": false
    },
    {
      "id": "tg-mmirleb-14808",
      "time": "2026-04-10T15:50:22+00:00",
      "title": "دفاعًا عن لبنان وشعبه، وردًّا على خرق العدوّ لاتفاق وقف إطلاق النار، واعتداءاته المتكرّرة على قرى ال",
      "description": "&rlm;  &rlm;&rlm;  دفاعًا عن لبنان وشعبه، وردًّا على خرق العدوّ لاتفاق وقف إطلاق النار، واعتداءاته المتكرّرة على قرى الجنوب، وبعدما التزمت المقاومة بوقف النار ولم يلتزم به العدوّ، استهدف مجاهدو المُقاومة الإسلاميّة عند السّاعة 16:40 الجمعة 10-04-2026 تجمّعًا لآليات وجنود جيش العدوّ الإسرائيليّ في مح",
      "category": "hezbollah",
      "status": "confirmed",
      "source": "@mmirleb",
      "needsReview": false,
      "lat": 33.29,
      "lon": 35.42
    },
    {
      "id": "tg-unewschannel-319233",
      "time": "2026-04-10T15:44:44+00:00",
      "title": "رئيس مجلس الوزراء اللبناني نواف سلام: أقدّم\"أصدق التعازي لأهل النبطية بشهدائها من المدنيين وعناصر أم",
      "description": "عاجل | رئيس مجلس الوزراء اللبناني نواف سلام: أقدّم\"أصدق التعازي لأهل النبطية بشهدائها من المدنيين وعناصر أمن الدولة الذين سقطوا جرّاء الاعتداءات الإسرائيلية التي طالت سرايا النبطية الحكومية ومحيطها وسوقها ولذوي الشهداء وعائلاتهم والمديرية العامة لأمن الدولة  عاجل | نواف سلام: هذا المصاب الأليم يزيدن",
      "category": "iran",
      "status": "developing",
      "source": "@unewschannel",
      "needsReview": false,
      "lat": 33.38,
      "lon": 35.49
    },
    {
      "id": "tg-unewschannel-319232",
      "time": "2026-04-10T15:44:03+00:00",
      "title": "رئيس مجلس الوزراء اللبناني نواف سلام: أقدّم\"أصدق التعازي لأهل النبطية بشهدائها من المدنيين وعناصر أم",
      "description": "عاجل | رئيس مجلس الوزراء اللبناني نواف سلام: أقدّم\"أصدق التعازي لأهل النبطية بشهدائها من المدنيين وعناصر أمن الدولة الذين سقطوا جرّاء الاعتداءات الإسرائيلية التي طالت سرايا النبطية الحكومية ومحيطها وسوقها ولذوي الشهداء وعائلاتهم والمديرية العامة لأمن الدولة",
      "category": "iran",
      "status": "developing",
      "source": "@unewschannel",
      "needsReview": false,
      "lat": 33.38,
      "lon": 35.49
    },
    {
      "id": "tg-unewschannel-319231",
      "time": "2026-04-10T15:42:23+00:00",
      "title": "رئيس مجلس النواب نبيه بري يجري إتصالا بقيادة جهاز أمن الدولة معزياً بالشهداء الذين سقطوا اليوم جراء ",
      "description": "عاجل | رئيس مجلس النواب نبيه بري يجري إتصالا بقيادة جهاز أمن الدولة معزياً بالشهداء الذين سقطوا اليوم جراء الغارات الإسرائيلية التي استهدفت مدينة النبطية متمنياً للجرحى الشفاء العاجل",
      "category": "enemy",
      "status": "developing",
      "source": "@unewschannel",
      "needsReview": false,
      "lat": 33.38,
      "lon": 35.49
    },
    {
      "id": "tg-unewschannel-319230",
      "time": "2026-04-10T15:39:37+00:00",
      "title": "المُقاومة الإسلاميّة في  تستهدف عند السّاعة 15:00 الجمعة 10-04-2026 عددًا من الجرّافات التابعة لجيش ",
      "description": "عاجل | المُقاومة الإسلاميّة في  تستهدف عند السّاعة 15:00 الجمعة 10-04-2026 عددًا من الجرّافات التابعة لجيش العدوّ الإسرائيلي كانت تعمل على هدم المنازل في بلدة عيتا الشعب بصليةٍ صاروخيّة",
      "category": "hezbollah",
      "status": "developing",
      "source": "@unewschannel",
      "needsReview": false,
      "lat": 33.28,
      "lon": 35.41
    },
    {
      "id": "tg-unewschannel-319229",
      "time": "2026-04-10T15:37:58+00:00",
      "title": "المديرية العامة لأمن الدولة: بتاريخ ١٠/٤/٢٠٢٦، استهدفت غارات إسرائيلية مبنى سرايا النبطية الحكومية ا",
      "description": "عاجل | المديرية العامة لأمن الدولة: بتاريخ ١٠/٤/٢٠٢٦، استهدفت غارات إسرائيلية مبنى سرايا النبطية الحكومية الذي تتمركز فيه مديرية النبطية الإقليمية لأمن الدولة، ما أدى إلى استشهاد ١٣ عنصرًا كانوا يواصلون أداء مهامهم في خدمة المواطنين في ظل الظروف الدقيقة التي…  عاجل | المديرية العامة لأمن الدولة تستن",
      "category": "enemy",
      "status": "developing",
      "source": "@unewschannel",
      "needsReview": false,
      "lat": 33.38,
      "lon": 35.49
    },
    {
      "id": "tg-unewschannel-319228",
      "time": "2026-04-10T15:37:18+00:00",
      "title": "المديرية العامة لأمن الدولة: بتاريخ ١٠/٤/٢٠٢٦، استهدفت غارات إسرائيلية مبنى سرايا النبطية الحكومية ا",
      "description": "عاجل | المديرية العامة لأمن الدولة: بتاريخ ١٠/٤/٢٠٢٦، استهدفت غارات إسرائيلية مبنى سرايا النبطية الحكومية الذي تتمركز فيه مديرية النبطية الإقليمية لأمن الدولة، ما أدى إلى استشهاد ١٣ عنصرًا كانوا يواصلون أداء مهامهم في خدمة المواطنين في ظل الظروف الدقيقة التي يمر بها  💔1",
      "category": "enemy",
      "status": "developing",
      "source": "@unewschannel",
      "needsReview": false,
      "lat": 33.38,
      "lon": 35.49
    },
    {
      "id": "tg-mmirleb-14806",
      "time": "2026-04-10T15:28:27+00:00",
      "title": "دفاعًا عن لبنان وشعبه، وردًّا على خرق العدوّ لاتفاق وقف إطلاق النار واستهداف مبنى السراي الحكومي في",
      "description": "&rlm;  &rlm;&rlm;  دفاعًا عن لبنان وشعبه، وردًّا على خرق العدوّ لاتفاق وقف إطلاق النار واستهداف مبنى السراي الحكومي في مدينة النبطية وبعدما التزمت المقاومة بوقف النار ولم يلتزم به العدوّ، استهدف مجاهدو المُقاومة الإسلاميّة عند السّاعة 18:00 الجمعة 10-04-2026 مستوطنتي ليمان وشلومي بصلياتٍ صاروخيّة. إ",
      "category": "hezbollah",
      "status": "confirmed",
      "source": "@mmirleb",
      "needsReview": false,
      "lat": 33.38,
      "lon": 35.49
    },
    {
      "id": "tg-mmirleb-14802",
      "time": "2026-04-10T14:55:08+00:00",
      "title": "دفاعًا عن لبنان وشعبه، وردًّا على خرق العدوّ لاتفاق وقف إطلاق النار، واعتداءاته المتكرّرة على قرى ال",
      "description": "&rlm;  &rlm;&rlm;  دفاعًا عن لبنان وشعبه، وردًّا على خرق العدوّ لاتفاق وقف إطلاق النار، واعتداءاته المتكرّرة على قرى الجنوب، وبعدما التزمت المقاومة بوقف النار ولم يلتزم به العدوّ، استهدف مجاهدو المُقاومة الإسلاميّة عند السّاعة 15:00 الجمعة 10-04-2026 عددًا من الجرّافات التابعة لجيش العدوّ الإسرائيلي",
      "category": "hezbollah",
      "status": "confirmed",
      "source": "@mmirleb",
      "needsReview": false,
      "lat": 33.28,
      "lon": 35.41
    },
    {
      "id": "tg-mmirleb-14801",
      "time": "2026-04-10T14:55:00+00:00",
      "title": "دفاعًا عن لبنان وشعبه، وردًّا على خرق العدوّ لاتفاق وقف إطلاق النار، واعتداءاته المتكرّرة على مدينة",
      "description": "&rlm;  &rlm;&rlm;  دفاعًا عن لبنان وشعبه، وردًّا على خرق العدوّ لاتفاق وقف إطلاق النار، واعتداءاته المتكرّرة على مدينة صور، وبعدما التزمت المقاومة بوقف النار ولم يلتزم به العدوّ، استهدف مجاهدو المُقاومة الإسلاميّة عند السّاعة 17:00 الجمعة 10-04-2026 مستوطنة نهاريّا بصليةٍ صاروخيّة. إنّ هذا الردّ سيس",
      "category": "hezbollah",
      "status": "confirmed",
      "source": "@mmirleb",
      "needsReview": false,
      "lat": 33.27,
      "lon": 35.2
    },
    {
      "id": "tg-almayadeen-364491",
      "time": "2026-04-10T13:16:23+00:00",
      "title": "اليمن: بيان المسيرات المليونية: نؤكد على ضرورة تثبيت معادلة الردع ووحدة الساحات وإسقاط معادلة الاستباحة والتجزئة للأمة ورفض تنفيذ مخطط \"إسرائيل الكبرى\"",
      "description": "اليمن: بيان المسيرات المليونية: نؤكد على ضرورة تثبيت معادلة الردع ووحدة الساحات وإسقاط معادلة الاستباحة والتجزئة للأمة ورفض تنفيذ مخطط \"إسرائيل الكبرى\"",
      "category": "statements",
      "status": "confirmed",
      "source": "@almayadeen",
      "needsReview": false,
      "lat": 15.37,
      "lon": 44.19
    },
    {
      "id": "tg-almayadeen-364490",
      "time": "2026-04-10T13:16:04+00:00",
      "title": "اليمن: بيان المسيرات المليونية: نؤكد مواقفنا الثابتة والمبدئية تجاه الشعب الفلسطيني والمسجد الأقصى وقضايا الأمة",
      "description": "اليمن: بيان المسيرات المليونية: نؤكد مواقفنا الثابتة والمبدئية تجاه الشعب الفلسطيني والمسجد الأقصى وقضايا الأمة",
      "category": "statements",
      "status": "confirmed",
      "source": "@almayadeen",
      "needsReview": false,
      "lat": 15.37,
      "lon": 44.19
    },
    {
      "id": "tg-almayadeen-364489",
      "time": "2026-04-10T13:15:08+00:00",
      "title": "لبنان: مراسل الميادين: 3 شهداء في العدوان الإسرائيلي على سحمر ودروس في البقاع شرق لبنان",
      "description": "لبنان: مراسل الميادين: 3 شهداء في العدوان الإسرائيلي على سحمر ودروس في البقاع شرق لبنان",
      "category": "statements",
      "status": "confirmed",
      "source": "@almayadeen",
      "needsReview": false,
      "lat": 33.85,
      "lon": 36.05
    },
    {
      "id": "tg-almayadeen-364488",
      "time": "2026-04-10T13:13:55+00:00",
      "title": "وسائل إعلام إسرائيلية: أنباء عن إصابة صاروخ لمبنى سكني في صفد",
      "description": "وسائل إعلام إسرائيلية: أنباء عن إصابة صاروخ لمبنى سكني في صفد",
      "category": "statements",
      "status": "confirmed",
      "source": "@almayadeen",
      "needsReview": false,
      "lat": 32.96,
      "lon": 35.5
    },
    {
      "id": "tg-almayadeen-364487",
      "time": "2026-04-10T13:13:18+00:00",
      "title": "لبنان: المقاومة الإسلامية: استهدفنا بنى تحتية تتبع لـ\"جيش\" العدو الإسرائيلي في مستوطنة \"كرميئيل\" بصلية صاروخية",
      "description": "لبنان: المقاومة الإسلامية: استهدفنا بنى تحتية تتبع لـ\"جيش\" العدو الإسرائيلي في مستوطنة \"كرميئيل\" بصلية صاروخية",
      "category": "hezbollah",
      "status": "confirmed",
      "source": "@almayadeen",
      "needsReview": false
    },
    {
      "id": "tg-unewschannel-319200",
      "time": "2026-04-10T13:12:22+00:00",
      "title": "القناة 14 العبرية: سقوط صاروخ من  في منطقة صفد",
      "description": "عاجل | القناة 14 العبرية: سقوط صاروخ من  في منطقة صفد 🔥1",
      "category": "iran",
      "status": "developing",
      "source": "@unewschannel",
      "needsReview": false,
      "lat": 32.96,
      "lon": 35.5
    },
    {
      "id": "tg-mmirleb-14786",
      "time": "2026-04-10T13:11:04+00:00",
      "title": "دفاعًا عن لبنان وشعبه، وردًّا على خرق العدوّ لاتفاق وقف إطلاق النار، واعتداءاته المتكرّرة على قرى ال",
      "description": "&rlm;  &rlm;&rlm;  دفاعًا عن لبنان وشعبه، وردًّا على خرق العدوّ لاتفاق وقف إطلاق النار، واعتداءاته المتكرّرة على قرى الجنوب، وبعدما التزمت المقاومة بوقف النار ولم يلتزم به العدوّ، استهدف مجاهدو المُقاومة الإسلاميّة عند السّاعة 14:50 الجمعة 10-04-2026 بنى تحتيّة تتبع لجيش العدوّ الإسرائيليّ في مستوطن",
      "category": "hezbollah",
      "status": "confirmed",
      "source": "@mmirleb",
      "needsReview": false
    },
    {
      "id": "tg-almayadeen-364486",
      "time": "2026-04-10T13:07:04+00:00",
      "title": "فلسطين المحتلة: صفارات الإنذار تدوي في صفد ومحيطها",
      "description": "فلسطين المحتلة: صفارات الإنذار تدوي في صفد ومحيطها",
      "category": "statements",
      "status": "confirmed",
      "source": "@almayadeen",
      "needsReview": false,
      "lat": 32.96,
      "lon": 35.5
    },
    {
      "id": "tg-almayadeen-364485",
      "time": "2026-04-10T13:04:07+00:00",
      "title": "وسائل إعلام إسرائيلية: \"هآرتس\": بالنسبة لإيران، فلم يقتصر الأمر على عدم تغير النظام بل ودفعت ترامب إلى إعلان وقف إطلاق النار بشكل شبه أحادي",
      "description": "وسائل إعلام إسرائيلية: \"هآرتس\": بالنسبة لإيران، فلم يقتصر الأمر على عدم تغير النظام بل ودفعت ترامب إلى إعلان وقف إطلاق النار بشكل شبه أحادي",
      "category": "iran",
      "status": "confirmed",
      "source": "@almayadeen",
      "needsReview": false
    },
    {
      "id": "tg-almayadeen-364484",
      "time": "2026-04-10T13:03:40+00:00",
      "title": "وسائل إعلام إسرائيلية: \"هآرتس\": الواقع لا ينصاع للشعارات.. حماس لم تتم تصفيتها وحزب الله لم يُحسم أمره والمواجهة في الشمال مستمرة بكثافة",
      "description": "وسائل إعلام إسرائيلية: \"هآرتس\": الواقع لا ينصاع للشعارات.. حماس لم تتم تصفيتها وحزب الله لم يُحسم أمره والمواجهة في الشمال مستمرة بكثافة",
      "category": "hezbollah",
      "status": "confirmed",
      "source": "@almayadeen",
      "needsReview": false,
      "lat": 33.1,
      "lon": 35.4
    },
    {
      "id": "tg-almayadeen-364483",
      "time": "2026-04-10T13:02:00+00:00",
      "title": "لبنان: المقاومة الإسلامية: ردنا سيستمر إلى أن يتوقف العدوان الإسرائيلي الأميركي على بلدنا وشعبنا",
      "description": "لبنان: المقاومة الإسلامية: ردنا سيستمر إلى أن يتوقف العدوان الإسرائيلي الأميركي على بلدنا وشعبنا",
      "category": "hezbollah",
      "status": "confirmed",
      "source": "@almayadeen",
      "needsReview": false
    },
    {
      "id": "tg-almayadeen-364482",
      "time": "2026-04-10T13:01:11+00:00",
      "title": "لبنان: المقاومة الإسلامية: استهدفنا آلية \"هامر\" في بلدة الطيبة بمحلقة انقضاضية وحققنا فيها إصابة مباشرة",
      "description": "لبنان: المقاومة الإسلامية: استهدفنا آلية \"هامر\" في بلدة الطيبة بمحلقة انقضاضية وحققنا فيها إصابة مباشرة",
      "category": "hezbollah",
      "status": "confirmed",
      "source": "@almayadeen",
      "needsReview": false,
      "lat": 33.34,
      "lon": 35.52
    },
    {
      "id": "tg-almayadeen-364481",
      "time": "2026-04-10T12:59:16+00:00",
      "title": "وسائل إعلام إسرائيلية: السفير اللبناني لدى واشنطن تحدث هاتفياً مع سفير \"إسرائيل\" تمهيداً للمحادثات المقرر عقدها الأسبوع المقبل",
      "description": "وسائل إعلام إسرائيلية: السفير اللبناني لدى واشنطن تحدث هاتفياً مع سفير \"إسرائيل\" تمهيداً للمحادثات المقرر عقدها الأسبوع المقبل",
      "category": "statements",
      "status": "confirmed",
      "source": "@almayadeen",
      "needsReview": false
    },
    {
      "id": "tg-almayadeen-364480",
      "time": "2026-04-10T12:52:24+00:00",
      "title": "لبنان: المقاومة الإسلامية: استهدفنا تجمعاً لجنود \"جيش\" العدو الإسرائيلي في بلدة رشاف بصلية صاروخية",
      "description": "لبنان: المقاومة الإسلامية: استهدفنا تجمعاً لجنود \"جيش\" العدو الإسرائيلي في بلدة رشاف بصلية صاروخية",
      "category": "hezbollah",
      "status": "confirmed",
      "source": "@almayadeen",
      "needsReview": false
    },
    {
      "id": "tg-unewschannel-319198",
      "time": "2026-04-10T12:51:08+00:00",
      "title": "يعلن استهداف تجمّع لجنود جيش العدوّ الإسرائيليّ في بلدة رشاف بصليةٍ صاروخيّة",
      "description": "عاجل |  يعلن استهداف تجمّع لجنود جيش العدوّ الإسرائيليّ في بلدة رشاف بصليةٍ صاروخيّة 🙏1",
      "category": "iran",
      "status": "developing",
      "source": "@unewschannel",
      "needsReview": false
    },
    {
      "id": "tg-mmirleb-14780",
      "time": "2026-04-10T12:50:09+00:00",
      "title": "دفاعًا عن لبنان وشعبه، وردًّا على خرق العدوّ لاتفاق وقف إطلاق النار، واعتداءاته المتكرّرة على قرى ال",
      "description": "&rlm;  &rlm;&rlm;  دفاعًا عن لبنان وشعبه، وردًّا على خرق العدوّ لاتفاق وقف إطلاق النار، واعتداءاته المتكرّرة على قرى الجنوب، وبعدما التزمت المقاومة بوقف النار ولم يلتزم به العدوّ، استهدف مجاهدو المُقاومة الإسلاميّة عند السّاعة 15:15 الجمعة 10-04-2026 آلية هامر في بلدة الطيبة بمحلّقة انقضاضيّة، وحققو",
      "category": "hezbollah",
      "status": "confirmed",
      "source": "@mmirleb",
      "needsReview": false,
      "lat": 33.34,
      "lon": 35.52
    },
    {
      "id": "tg-unewschannel-319197",
      "time": "2026-04-10T12:47:37+00:00",
      "title": "نائب الرئيس الأمريكي: سنعمل على أن تكون المفاوضات في باكستان إيجابية",
      "description": "عاجل | نائب الرئيس الأمريكي: سنعمل على أن تكون المفاوضات في باكستان إيجابية  عاجل | نائب الرئيس الأمريكي: الرئيس قدم لنا توجيهات واضحة للغاية حول مفاوضات إسلام آباد وسنرى ما ستؤول إليه الأمور",
      "category": "political",
      "status": "developing",
      "source": "@unewschannel",
      "needsReview": false
    },
    {
      "id": "tg-unewschannel-319196",
      "time": "2026-04-10T12:47:27+00:00",
      "title": "نائب الرئيس الأمريكي: إذا حاول الإيرانيون المناورة فسيرون أن فريقنا التفاوضي لن يكون متجاوباً معهم",
      "description": "عاجل | نائب الرئيس الأمريكي: إذا حاول الإيرانيون المناورة فسيرون أن فريقنا التفاوضي لن يكون متجاوباً معهم  عاجل | نائب الرئيس الأمريكي: سنعمل على أن تكون المفاوضات في باكستان إيجابية",
      "category": "iran",
      "status": "developing",
      "source": "@unewschannel",
      "needsReview": false
    },
    {
      "id": "tg-unewschannel-319195",
      "time": "2026-04-10T12:46:48+00:00",
      "title": "نائب الرئيس الأمريكي: نحن مستعدون بالتأكيد لمد يد التعاون في مفاوضات إسلام آباد",
      "description": "عاجل | نائب الرئيس الأمريكي: نحن مستعدون بالتأكيد لمد يد التعاون في مفاوضات إسلام آباد  عاجل | نائب الرئيس الأمريكي: إذا حاول الإيرانيون المناورة فسيرون أن فريقنا التفاوضي لن يكون متجاوباً معهم",
      "category": "iran",
      "status": "developing",
      "source": "@unewschannel",
      "needsReview": false
    },
    {
      "id": "tg-unewschannel-319194",
      "time": "2026-04-10T12:46:35+00:00",
      "title": "نائب الرئيس الأمريكي: سنرى ما إذا كان الإيرانيون مستعدين للتفاوض بحسن نية",
      "description": "عاجل | نائب الرئيس الأمريكي: سنرى ما إذا كان الإيرانيون مستعدين للتفاوض بحسن نية  عاجل | نائب الرئيس الأمريكي: نحن مستعدون بالتأكيد لمد يد التعاون في مفاوضات إسلام آباد",
      "category": "iran",
      "status": "developing",
      "source": "@unewschannel",
      "needsReview": false
    },
    {
      "id": "tg-almayadeen-364479",
      "time": "2026-04-10T12:46:13+00:00",
      "title": "لبنان: مراسل الميادين في الجنوب: شهداء وجرحى من عناصر جهاز أمن الدولة اللبنانية من جراء العدوان الإسرائيلي الذي استهدف محيط السراي الحكومي في النبطية",
      "description": "لبنان: مراسل الميادين في الجنوب: شهداء وجرحى من عناصر جهاز أمن الدولة اللبنانية من جراء العدوان الإسرائيلي الذي استهدف محيط السراي الحكومي في النبطية",
      "category": "statements",
      "status": "confirmed",
      "source": "@almayadeen",
      "needsReview": false,
      "lat": 33.38,
      "lon": 35.49
    },
    {
      "id": "tg-unewschannel-319193",
      "time": "2026-04-10T12:44:57+00:00",
      "title": "نائب الرئيس الأمريكي قبيل توجهه إلى باكستان: نتطلع للمفاوضات مع  ونتمنى أن تكون إيجابية",
      "description": "عاجل | نائب الرئيس الأمريكي قبيل توجهه إلى باكستان: نتطلع للمفاوضات مع  ونتمنى أن تكون إيجابية  عاجل | نائب الرئيس الأمريكي: سنرى ما إذا كان الإيرانيون مستعدين للتفاوض بحسن نية",
      "category": "iran",
      "status": "developing",
      "source": "@unewschannel",
      "needsReview": false
    },
    {
      "id": "tg-unewschannel-319192",
      "time": "2026-04-10T12:44:45+00:00",
      "title": "نائب الرئيس الأمريكي \"جيه دي فانس\" يغادر متجهاً إلى إسلام أباد للمشاركة في المفاوضات مع",
      "description": "عاجل | نائب الرئيس الأمريكي \"جيه دي فانس\" يغادر متجهاً إلى إسلام أباد للمشاركة في المفاوضات مع   عاجل | نائب الرئيس الأمريكي قبيل توجهه إلى باكستان: نتطلع للمفاوضات مع  ونتمنى أن تكون إيجابية",
      "category": "political",
      "status": "developing",
      "source": "@unewschannel",
      "needsReview": false
    },
    {
      "id": "tg-almayadeen-364478",
      "time": "2026-04-10T12:43:10+00:00",
      "title": "وسائل إعلام إسرائيلية: 4 إصابات في هجمات حزب الله على الشمال",
      "description": "وسائل إعلام إسرائيلية: 4 إصابات في هجمات حزب الله على الشمال",
      "category": "hezbollah",
      "status": "confirmed",
      "source": "@almayadeen",
      "needsReview": false,
      "lat": 33.1,
      "lon": 35.4
    },
    {
      "id": "tg-unewschannel-319191",
      "time": "2026-04-10T12:37:17+00:00",
      "title": "نائب الرئيس الأمريكي \"جيه دي فانس\" يغادر متجهاً إلى إسلام أباد للمشاركة في المفاوضات مع",
      "description": "عاجل | نائب الرئيس الأمريكي \"جيه دي فانس\" يغادر متجهاً إلى إسلام أباد للمشاركة في المفاوضات مع",
      "category": "political",
      "status": "developing",
      "source": "@unewschannel",
      "needsReview": false
    },
    {
      "id": "tg-almayadeen-364477",
      "time": "2026-04-10T12:35:44+00:00",
      "title": "الولايات المتحدة الأميركية: نائب الرئيس الأميركي جيه دي فانس: أتطلع إلى مفاوضات إيران وأعتقد أنها ستكون بناءة",
      "description": "الولايات المتحدة الأميركية: نائب الرئيس الأميركي جيه دي فانس: أتطلع إلى مفاوضات إيران وأعتقد أنها ستكون بناءة",
      "category": "iran",
      "status": "confirmed",
      "source": "@almayadeen",
      "needsReview": false
    },
    {
      "id": "tg-almayadeen-364476",
      "time": "2026-04-10T12:34:30+00:00",
      "title": "\"اليونيسيف\": \"إسرائيل\" شنت غارات جوية مميتة على لبنان أسفرت عن \"مقتل\" 33 طفلاً وإصابة 153 آخرين في الوقت الذي أشعلت أنباء اتفاق وقف إطلاق النار الإقليمي بصيص أمل في أرجاء البلاد",
      "description": "\"اليونيسيف\": \"إسرائيل\" شنت غارات جوية مميتة على لبنان أسفرت عن \"مقتل\" 33 طفلاً وإصابة 153 آخرين في الوقت الذي أشعلت أنباء اتفاق وقف إطلاق النار الإقليمي بصيص أمل في أرجاء البلاد",
      "category": "enemy",
      "status": "confirmed",
      "source": "@almayadeen",
      "needsReview": false
    },
    {
      "id": "tg-almayadeen-364475",
      "time": "2026-04-10T12:32:29+00:00",
      "title": "\"اليونيسيف\": لا يزال تصاعد الأعمال العدائية في لبنان يُلحق خسائر فادحة وغير إنسانية بالأطفال",
      "description": "\"اليونيسيف\": لا يزال تصاعد الأعمال العدائية في لبنان يُلحق خسائر فادحة وغير إنسانية بالأطفال",
      "category": "statements",
      "status": "confirmed",
      "source": "@almayadeen",
      "needsReview": false
    },
    {
      "id": "tg-almayadeen-364474",
      "time": "2026-04-10T12:31:50+00:00",
      "title": "اليمن: مراسل الميادين: مسيرات مليونية في ميدان السبعين بالعاصمة صنعاء ومئات الساحات في عدة محافظات نصرة للبنان وفلسطين ومباركة لإيران في الانتصار على العدوان الأميركي الإسرائيلي",
      "description": "اليمن: مراسل الميادين: مسيرات مليونية في ميدان السبعين بالعاصمة صنعاء ومئات الساحات في عدة محافظات نصرة للبنان وفلسطين ومباركة لإيران في الانتصار على العدوان الأميركي الإسرائيلي",
      "category": "iran",
      "status": "confirmed",
      "source": "@almayadeen",
      "needsReview": false,
      "lat": 15.37,
      "lon": 44.19
    },
    {
      "id": "tg-almayadeen-364473",
      "time": "2026-04-10T12:30:24+00:00",
      "title": "لبنان: مراسل الميادين في الجنوب: إصابات في صفوف عناصر أمن الدولة من جراء اعتداء إسرائيلي استهدف محيط السراي الحكومي في مدينة النبطية",
      "description": "لبنان: مراسل الميادين في الجنوب: إصابات في صفوف عناصر أمن الدولة من جراء اعتداء إسرائيلي استهدف محيط السراي الحكومي في مدينة النبطية",
      "category": "statements",
      "status": "confirmed",
      "source": "@almayadeen",
      "needsReview": false,
      "lat": 33.38,
      "lon": 35.49
    },
    {
      "id": "tg-almayadeen-364472",
      "time": "2026-04-10T12:29:10+00:00",
      "title": "وسائل إعلام إسرائيلية: \"هآرتس\": \"إسرائيل\" فشلت في قراءة الخريطة ولبنان أصبح ورقة حاسمة في المفاوضات بين إيران والولايات المتحدة",
      "description": "وسائل إعلام إسرائيلية: \"هآرتس\": \"إسرائيل\" فشلت في قراءة الخريطة ولبنان أصبح ورقة حاسمة في المفاوضات بين إيران والولايات المتحدة",
      "category": "iran",
      "status": "confirmed",
      "source": "@almayadeen",
      "needsReview": false
    },
    {
      "id": "tg-unewschannel-319189",
      "time": "2026-04-10T12:26:11+00:00",
      "title": "هام | إذاعة الجيش الإسرائيلي: المجلس الوزاري المصغر يجتمع منذ عدة ساعات، في ظل الضغط الأمريكي لتقليل",
      "description": "هام | إذاعة الجيش الإسرائيلي: المجلس الوزاري المصغر يجتمع منذ عدة ساعات، في ظل الضغط الأمريكي لتقليل شدة العمليات العسكرية في   هام | صحيفة \"معاريف\" العبرية: الكابينيت الأمني والسياسي الإسرائيلي مجتمع منذ ثلاث ساعات لبحث  و",
      "category": "iran",
      "status": "confirmed",
      "source": "@unewschannel",
      "needsReview": false
    },
    {
      "id": "tg-unewschannel-319188",
      "time": "2026-04-10T12:22:58+00:00",
      "title": "هام | إذاعة الجيش الإسرائيلي: المجلس الوزاري المصغر يجتمع منذ عدة ساعات، في ظل الضغط الأمريكي لتقليل",
      "description": "هام | إذاعة الجيش الإسرائيلي: المجلس الوزاري المصغر يجتمع منذ عدة ساعات، في ظل الضغط الأمريكي لتقليل شدة العمليات العسكرية في",
      "category": "iran",
      "status": "confirmed",
      "source": "@unewschannel",
      "needsReview": false
    },
    {
      "id": "tg-unewschannel-319187",
      "time": "2026-04-10T12:15:56+00:00",
      "title": "القناة 12 العبرية: أضرار في مبانٍ ومدرسة في منطقة كرمئيل والمناطق المحيطة جراء القصف الصاروخي الأخير",
      "description": "عاجل | القناة 12 العبرية: أضرار في مبانٍ ومدرسة في منطقة كرمئيل والمناطق المحيطة جراء القصف الصاروخي الأخير من",
      "category": "iran",
      "status": "developing",
      "source": "@unewschannel",
      "needsReview": false
    },
    {
      "id": "tg-unewschannel-319186",
      "time": "2026-04-10T12:11:02+00:00",
      "title": "يعلن استهداف تجمّع لجنود جيش العدوّ الإسرائيليّ عند مثلث التحرير على أطراف مدينة بنت جبيل بصليةٍ صار",
      "description": "عاجل |  يعلن استهداف تجمّع لجنود جيش العدوّ الإسرائيليّ عند مثلث التحرير على أطراف مدينة بنت جبيل بصليةٍ صاروخيّة ❤1🔥1",
      "category": "hezbollah",
      "status": "developing",
      "source": "@unewschannel",
      "needsReview": false,
      "lat": 33.29,
      "lon": 35.42
    },
    {
      "id": "tg-unewschannel-319185",
      "time": "2026-04-10T12:10:22+00:00",
      "title": "الشيخ قاسم: نحن معًا كدولة وجيش وشعب ومقاومة نحمي بلدنا ونُعيد سيادته ونطرد المحتل",
      "description": "عاجل | الشيخ قاسم: نحن معًا كدولة وجيش وشعب ومقاومة نحمي بلدنا ونُعيد سيادته ونطرد المحتل  عاجل | الشيخ قاسم: لن تخيفنا تهديداتهم ولا أسلحتهم، فنحن أصحاب الأرض، نملك الإيمان والإرادة والقدرة لنمنعهم من تحقيق أهدافهم ❤1👍1",
      "category": "iran",
      "status": "developing",
      "source": "@unewschannel",
      "needsReview": false
    },
    {
      "id": "tg-mmirleb-14778",
      "time": "2026-04-10T12:10:09+00:00",
      "title": "دفاعًا عن لبنان وشعبه، وردًّا على خرق العدوّ لاتفاق وقف إطلاق النار، واعتداءاته المتكرّرة على قرى ال",
      "description": "&rlm;  &rlm;&rlm;  دفاعًا عن لبنان وشعبه، وردًّا على خرق العدوّ لاتفاق وقف إطلاق النار، واعتداءاته المتكرّرة على قرى الجنوب، وبعدما التزمت المقاومة بوقف النار ولم يلتزم به العدوّ، استهدف مجاهدو المُقاومة الإسلاميّة عند السّاعة 12:20 الجمعة 10-04-2026 تجمّعًا لجنود جيش العدوّ الإسرائيليّ في بلدة رشاف",
      "category": "hezbollah",
      "status": "confirmed",
      "source": "@mmirleb",
      "needsReview": false
    },
    {
      "id": "tg-mmirleb-14777",
      "time": "2026-04-10T12:10:00+00:00",
      "title": "دفاعًا عن لبنان وشعبه، وردًّا على خرق العدوّ لاتفاق وقف إطلاق النار، واعتداءاته المتكرّرة على قرى ال",
      "description": "&rlm;  &rlm;&rlm;  دفاعًا عن لبنان وشعبه، وردًّا على خرق العدوّ لاتفاق وقف إطلاق النار، واعتداءاته المتكرّرة على قرى الجنوب، وبعدما التزمت المقاومة بوقف النار ولم يلتزم به العدوّ، استهدف مجاهدو المُقاومة الإسلاميّة عند السّاعة 09:40 الجمعة 10-04-2026 تجمّعًا لجنود جيش العدوّ الإسرائيليّ عند مثلث الت",
      "category": "hezbollah",
      "status": "confirmed",
      "source": "@mmirleb",
      "needsReview": false,
      "lat": 33.29,
      "lon": 35.42
    },
    {
      "id": "tg-unewschannel-319184",
      "time": "2026-04-10T12:09:56+00:00",
      "title": "الشيخ قاسم: لن نقبل بالعودة إلى الوضع السابق، وندعو المسؤولين إلى إيقاف التنازلات المجانية",
      "description": "عاجل | الشيخ قاسم: لن نقبل بالعودة إلى الوضع السابق، وندعو المسؤولين إلى إيقاف التنازلات المجانية  عاجل | الشيخ قاسم: نحن معًا كدولة وجيش وشعب ومقاومة نحمي بلدنا ونُعيد سيادته ونطرد المحتل ❤1👍1",
      "category": "iran",
      "status": "developing",
      "source": "@unewschannel",
      "needsReview": false
    },
    {
      "id": "tg-unewschannel-319183",
      "time": "2026-04-10T12:09:42+00:00",
      "title": "الشيخ قاسم: المقاومة مستمرة حتى ينقطع النفس، وتنافس الشباب إلى الميدان لا يغادرونه هو بارقة أمل وعزة",
      "description": "عاجل | الشيخ قاسم: المقاومة مستمرة حتى ينقطع النفس، وتنافس الشباب إلى الميدان لا يغادرونه هو بارقة أمل وعزة، والتضحيات تجعلنا أكثر تشبثًا بتحرير وطننا وكرامتنا  عاجل | الشيخ قاسم: لن نقبل بالعودة إلى الوضع السابق، وندعو المسؤولين إلى إيقاف التنازلات المجانية ❤1👍1",
      "category": "iran",
      "status": "developing",
      "source": "@unewschannel",
      "needsReview": false
    },
    {
      "id": "tg-unewschannel-319182",
      "time": "2026-04-10T12:09:14+00:00",
      "title": "الشيخ قاسم: العدو لجأ إلى الإجرام الدموي يوم الأربعاء في بيروت والضاحية والجنوب والبقاع وجبل لبنان و",
      "description": "عاجل | الشيخ قاسم: العدو لجأ إلى الإجرام الدموي يوم الأربعاء في بيروت والضاحية والجنوب والبقاع وجبل لبنان وفي كل مكان باستهداف المدنيين في الأحياء الممتدة والقرى والبلدات لتغطية عجزه في الميدان  عاجل | الشيخ قاسم: المقاومة مستمرة حتى ينقطع النفس، وتنافس الشباب إلى الميدان لا يغادرونه هو بارقة أمل وع",
      "category": "iran",
      "status": "developing",
      "source": "@unewschannel",
      "needsReview": false,
      "lat": 33.89,
      "lon": 35.51
    },
    {
      "id": "tg-unewschannel-319181",
      "time": "2026-04-10T12:08:46+00:00",
      "title": "الشيخ قاسم: تبيّن أنّ حشد مئة ألف جندي إسرائيلي لن يساعد العدو على الاحتلال، بل سيتحولون إلى جثث وأش",
      "description": "عاجل | الشيخ قاسم: تبيّن أنّ حشد مئة ألف جندي إسرائيلي لن يساعد العدو على الاحتلال، بل سيتحولون إلى جثث وأشلاء  عاجل | الشيخ قاسم: العدو لجأ إلى الإجرام الدموي يوم الأربعاء في بيروت والضاحية والجنوب والبقاع وجبل لبنان وفي كل مكان باستهداف المدنيين في الأحياء الممتدة والقرى والبلدات لتغطية عجزه في ال",
      "category": "iran",
      "status": "developing",
      "source": "@unewschannel",
      "needsReview": false,
      "lat": 33.89,
      "lon": 35.51
    },
    {
      "id": "tg-mmirleb-14775",
      "time": "2026-04-10T11:55:22+00:00",
      "title": "رسالة حجة الإسلام والمسلمين الأمين العام لحزب الله سماحة الشيخ نعيم قاسم للبنانيين الصامدين والمضحين:",
      "description": "رسالة حجة الإسلام والمسلمين الأمين العام لحزب الله سماحة الشيخ نعيم قاسم للبنانيين الصامدين والمضحين:  أُعزّي أهلنا الصابرين الصامدين في كل أنحاء لبنان الوطن بارتقاء الشهداء الأبرار من الرجال والنساء والأطفال والمجاهدين والمجاهدات، سائلاً المولى تعالى لهم أعظم الرحمات، لما قدّموه لشعبنا ووطننا من دم",
      "category": "hezbollah",
      "status": "developing",
      "source": "@mmirleb",
      "needsReview": false,
      "lat": 33.89,
      "lon": 35.51
    },
    {
      "id": "tg-mmirleb-14773",
      "time": "2026-04-10T11:45:06+00:00",
      "title": "دفاعًا عن لبنان وشعبه، وردًّا على خرق العدوّ لاتفاق وقف إطلاق النار، واعتداءاته المتكرّرة على قرى ال",
      "description": "&rlm;  &rlm;&rlm;  دفاعًا عن لبنان وشعبه، وردًّا على خرق العدوّ لاتفاق وقف إطلاق النار، واعتداءاته المتكرّرة على قرى الجنوب، وبعدما التزمت المقاومة بوقف النار ولم يلتزم به العدوّ، استهدف مجاهدو المُقاومة الإسلاميّة عند السّاعة 09:20 الجمعة 10-04-2026 تجمّعًا لجنود جيش العدوّ الإسرائيليّ في محيط موقع",
      "category": "hezbollah",
      "status": "confirmed",
      "source": "@mmirleb",
      "needsReview": false,
      "lat": 33.29,
      "lon": 35.41
    },
    {
      "id": "tg-mmirleb-14772",
      "time": "2026-04-10T11:45:03+00:00",
      "title": "دفاعًا عن لبنان وشعبه، وردًّا على خرق العدوّ لاتفاق وقف إطلاق النار، واعتداءاته المتكرّرة على قرى ال",
      "description": "&rlm;  &rlm;&rlm;  دفاعًا عن لبنان وشعبه، وردًّا على خرق العدوّ لاتفاق وقف إطلاق النار، واعتداءاته المتكرّرة على قرى الجنوب، وبعدما التزمت المقاومة بوقف النار ولم يلتزم به العدوّ، استهدف مجاهدو المُقاومة الإسلاميّة عند السّاعة 13:50 الجمعة 10-04-2026 مربض مدفعيّة للعدوّ الإسرائيليّ في مستوطنة نؤوت م",
      "category": "hezbollah",
      "status": "confirmed",
      "source": "@mmirleb",
      "needsReview": false
    },
    {
      "id": "tg-mmirleb-14767",
      "time": "2026-04-10T11:25:01+00:00",
      "title": "دفاعًا عن لبنان وشعبه، وردًّا على خرق العدوّ لاتفاق وقف إطلاق النار، واعتداءاته المتكرّرة على مدينة",
      "description": "&rlm;  &rlm;&rlm;  دفاعًا عن لبنان وشعبه، وردًّا على خرق العدوّ لاتفاق وقف إطلاق النار، واعتداءاته المتكرّرة على مدينة بيروت، وبعدما التزمت المقاومة بوقف النار ولم يلتزم به العدوّ، استهدف مجاهدو المُقاومة الإسلاميّة عند السّاعة 01:00 الجمعة 10-04-2026 القاعدة البحريّة العسكريّة في ميناء أشدود بصواري",
      "category": "hezbollah",
      "status": "confirmed",
      "source": "@mmirleb",
      "needsReview": false,
      "lat": 33.89,
      "lon": 35.51
    }
  ]
}